{"meta": {"filename": "089_199702_2_eve_annotated", "author": "unknown", "year": "1997", "recplace": "Bystraja district", "title": "Снова об оленеводстве", "genre": "newspaper"}, "sentences": [{"text": "НЯНДА ОРАМНАЛБА ИНЫВЭТЭН", "words": [{"wf": "НЯНДА", "off_start": 0, "off_end": 5, "wtype": "word", "ana": [{"parts": "n'an-da", "gloss": "и-ADD", "gloss_index": "и{n'an}-ADD{da}-"}], "next_word": 1, "sentence_index": 0, "sentence_index_neg": 3}, {"wf": "ОРАМНАЛБА", "off_start": 6, "off_end": 15, "wtype": "word", "ana": [{"parts": "ora-mna-lba", "gloss": "олень-AG.PROF-PL-ACC", "gloss_index": "олень{ora}-AG.PROF{mna}-PL{lba}-"}], "next_word": 2, "sentence_index": 1, "sentence_index_neg": 2}, {"wf": "ИНЫВЭТЭН", "off_start": 16, "off_end": 24, "wtype": "word", "ana": [{"parts": "inɨ-we-ten", "gloss": "жизнь-ACC-POSS.3PL", "gloss_index": "жизнь{inɨ}-ACC{we}-POSS.3PL{ten}-"}], "next_word": 3, "sentence_index": 2, "sentence_index_neg": 1}], "lang": 0, "para_alignment": [{"off_start": 0, "off_end": 24, "para_id": 0}]}, {"text": "Тык ини одыда эчусты ордула однэ.", "words": [{"wf": "Тык", "off_start": 0, "off_end": 3, "wtype": "word", "ana": [{"parts": "tɨk", "gloss": "сейчас", "gloss_index": "сейчас{tɨk}-"}], "next_word": 1, "sentence_index": 0, "sentence_index_neg": 6}, {"wf": "ини", "off_start": 4, "off_end": 7, "wtype": "word", "ana": [{"parts": "ini", "gloss": "жизнь", "gloss_index": "жизнь{ini}-"}], "next_word": 2, "sentence_index": 1, "sentence_index_neg": 5}, {"wf": "одыда", "off_start": 8, "off_end": 13, "wtype": "word", "ana": [{"parts": "od-di-da", "gloss": "стать-PTC.NFUT-ADD", "gloss_index": "стать{od}-PTC.NFUT{di}-ADD{da}-"}], "next_word": 3, "sentence_index": 2, "sentence_index_neg": 4}, {"wf": "эчусты", "off_start": 14, "off_end": 20, "wtype": "word", "ana": [{"parts": "ečus-ti", "gloss": "трудный-ADD", "gloss_index": "трудный{ečus}-ADD{ti}-"}], "next_word": 4, "sentence_index": 3, "sentence_index_neg": 3}, {"wf": "ордула", "off_start": 21, "off_end": 27, "wtype": "word", "ana": [{"parts": "or-dula", "gloss": "олень-LOC", "gloss_index": "олень{or}-LOC{dula}-"}], "next_word": 5, "sentence_index": 4, "sentence_index_neg": 2}, {"wf": "однэ.", "off_start": 28, "off_end": 33, "wtype": "word", "ana": [{"parts": "od-ne", "gloss": "стать-PST-3SG", "gloss_index": "стать{od}-PST{ne}-"}], "next_word": 6, "sentence_index": 5, "sentence_index_neg": 1}], "lang": 0, "para_alignment": [{"off_start": 0, "off_end": 33, "para_id": 1}]}, {"text": "Райондулат кэнели ордула, кэнели одыда Онавгаимӈылдула.", "words": [{"wf": "Райондулат", "off_start": 0, "off_end": 10, "wtype": "word", "ana": [{"parts": "rajon-dula-t", "gloss": "район-LOC-POSS.1PL.INC", "gloss_index": "район{rajon}-LOC{dula}-POSS.1PL.INC{t}-"}], "next_word": 1, "sentence_index": 0, "sentence_index_neg": 6}, {"wf": "кэнели", "off_start": 11, "off_end": 17, "wtype": "word", "ana": [{"parts": "ken'eli", "gloss": "плохой", "gloss_index": "плохой{ken'eli}-"}], "next_word": 2, "sentence_index": 1, "sentence_index_neg": 5}, {"wf": "ордула,", "off_start": 18, "off_end": 25, "wtype": "word", "ana": [{"parts": "or-dula", "gloss": "олень-LOC", "gloss_index": "олень{or}-LOC{dula}-"}], "next_word": 3, "sentence_index": 2, "sentence_index_neg": 4}, {"wf": "кэнели", "off_start": 26, "off_end": 32, "wtype": "word", "ana": [{"parts": "ken'eli", "gloss": "плохой", "gloss_index": "плохой{ken'eli}-"}], "next_word": 4, "sentence_index": 3, "sentence_index_neg": 3}, {"wf": "одыда", "off_start": 33, "off_end": 38, "wtype": "word", "ana": [{"parts": "od-di-da", "gloss": "стать-PTC.NFUT-ADD", "gloss_index": "стать{od}-PTC.NFUT{di}-ADD{da}-"}], "next_word": 5, "sentence_index": 4, "sentence_index_neg": 2}, {"wf": "Онавгаимӈылдула.", "off_start": 39, "off_end": 55, "wtype": "word", "ana": [{"parts": "onawgai-mŋɨ-l-dula", "gloss": "анавгай-AG.PROF-LOC", "gloss_index": "анавгай{onawgai}-AG.PROF{mŋɨ}-LOC{l}-"}], "next_word": 6, "sentence_index": 5, "sentence_index_neg": 1}], "lang": 0, "para_alignment": [{"off_start": 0, "off_end": 55, "para_id": 2}]}, {"text": "Табыч он индиддэ унтэмӈэл орымӈыл Тигильский районный газетадук «Панорама».", "words": [{"wf": "Табыч", "off_start": 0, "off_end": 5, "wtype": "word", "ana": [{"parts": "tabič", "gloss": "а.вон", "gloss_index": "а.вон{tabič}-"}], "next_word": 1, "sentence_index": 0, "sentence_index_neg": 9}, {"wf": "он", "off_start": 6, "off_end": 8, "wtype": "word", "ana": [{"parts": "on", "gloss": "как", "gloss_index": "как{on}-"}], "next_word": 2, "sentence_index": 1, "sentence_index_neg": 8}, {"wf": "индиддэ", "off_start": 9, "off_end": 16, "wtype": "word", "ana": [{"parts": "ind'i-d-de-∅", "gloss": "жить-PROG-NFUT-3PL", "gloss_index": "жить{ind'i}-PROG{d}-NFUT{de}-3PL{∅}-"}], "next_word": 3, "sentence_index": 2, "sentence_index_neg": 7}, {"wf": "унтэмӈэл", "off_start": 17, "off_end": 25, "wtype": "word", "ana": [{"parts": "unte-mŋe-l", "gloss": "другой-AG.PROF-PL", "gloss_index": "другой{unte}-AG.PROF{mŋe}-PL{l}-"}], "next_word": 4, "sentence_index": 3, "sentence_index_neg": 6}, {"wf": "орымӈыл", "off_start": 26, "off_end": 33, "wtype": "word", "ana": [{"parts": "orɨ-mŋɨ-l", "gloss": "олень-AG.PROF-PL", "gloss_index": "олень{orɨ}-AG.PROF{mŋɨ}-PL{l}-"}], "next_word": 5, "sentence_index": 4, "sentence_index_neg": 5}, {"wf": "Тигильский", "off_start": 34, "off_end": 44, "wtype": "word", "ana": [{"parts": "tigilskij", "gloss": "тигильский", "gloss_index": "тигильский{tigilskij}-"}], "next_word": 6, "sentence_index": 5, "sentence_index_neg": 4}, {"wf": "районный", "off_start": 45, "off_end": 53, "wtype": "word", "ana": [{"parts": "rajonnɨj", "gloss": "районный", "gloss_index": "районный{rajonnɨj}-"}], "next_word": 7, "sentence_index": 6, "sentence_index_neg": 3}, {"wf": "газетадук", "off_start": 54, "off_end": 63, "wtype": "word", "ana": [{"parts": "gaz'eta-duk", "gloss": "газета-ABL", "gloss_index": "газета{gaz'eta}-ABL{duk}-"}], "next_word": 8, "sentence_index": 7, "sentence_index_neg": 2}, {"wf": "«Панорама».", "off_start": 64, "off_end": 75, "wtype": "word", "ana": [{"parts": "panorama", "gloss": "панорама", "gloss_index": "панорама{panorama}-"}], "next_word": 9, "sentence_index": 8, "sentence_index_neg": 1}], "lang": 0, "para_alignment": [{"off_start": 0, "off_end": 75, "para_id": 3}]}, {"text": "Эдук нян мут унудип он гургэвчитды Магаданский областила, Чукоткала.", "words": [{"wf": "Эдук", "off_start": 0, "off_end": 4, "wtype": "word", "ana": [{"parts": "e-duk", "gloss": "dem.PROX-ABL", "gloss_index": "dem.PROX{e}-ABL{duk}-"}], "next_word": 1, "sentence_index": 0, "sentence_index_neg": 9}, {"wf": "нян", "off_start": 5, "off_end": 8, "wtype": "word", "ana": [{"parts": "n'an", "gloss": "и", "gloss_index": "и{n'an}-"}], "next_word": 2, "sentence_index": 1, "sentence_index_neg": 8}, {"wf": "мут", "off_start": 9, "off_end": 12, "wtype": "word", "ana": [{"parts": "mut", "gloss": "мы.EXC", "gloss_index": "мы.EXC{mut}-"}], "next_word": 3, "sentence_index": 2, "sentence_index_neg": 7}, {"wf": "унудип", "off_start": 13, "off_end": 19, "wtype": "word", "ana": [{"parts": "unu-d'i-p", "gloss": "понимать-FUT-1PL.INC", "gloss_index": "понимать{unu}-FUT{d'i}-1PL.INC{p}-"}], "next_word": 4, "sentence_index": 3, "sentence_index_neg": 6}, {"wf": "он", "off_start": 20, "off_end": 22, "wtype": "word", "ana": [{"parts": "on", "gloss": "как", "gloss_index": "как{on}-"}], "next_word": 5, "sentence_index": 4, "sentence_index_neg": 5}, {"wf": "гургэвчитды", "off_start": 23, "off_end": 34, "wtype": "word", "ana": [{"parts": "gurge-wči-t-dɨ-∅", "gloss": "работа-VBZ-PROG-NFUT-3PL", "gloss_index": "работа{gurge}-VBZ{wči}-PROG{t}-NFUT{dɨ}-3PL{∅}-"}], "next_word": 6, "sentence_index": 5, "sentence_index_neg": 4}, {"wf": "Магаданский", "off_start": 35, "off_end": 46, "wtype": "word", "ana": [{"parts": "magadanskij", "gloss": "Магаданский", "gloss_index": "Магаданский{magadanskij}-"}], "next_word": 7, "sentence_index": 6, "sentence_index_neg": 3}, {"wf": "областила,", "off_start": 47, "off_end": 57, "wtype": "word", "ana": [{"parts": "oblasti-la", "gloss": "область-LOC", "gloss_index": "область{oblasti}-LOC{la}-"}], "next_word": 8, "sentence_index": 7, "sentence_index_neg": 2}, {"wf": "Чукоткала.", "off_start": 58, "off_end": 68, "wtype": "word", "ana": [{"parts": "čukotka-la", "gloss": "Чукотка-LOC.", "gloss_index": "Чукотка{čukotka}-LOC.{la}-"}], "next_word": 9, "sentence_index": 8, "sentence_index_neg": 1}], "lang": 0, "para_alignment": [{"off_start": 0, "off_end": 68, "para_id": 4}]}, {"text": "НЕНЫТЭН ОРЫНЫЛ, ОРЫМӇЫЛДА", "words": [{"wf": "НЕНЫТЭН", "off_start": 0, "off_end": 7, "wtype": "word", "ana": [{"parts": "n'e-nɨ-ten", "gloss": "убежать-PST-3PL", "gloss_index": "убежать{n'e}-PST{nɨ}-3PL{ten}-"}], "next_word": 1, "sentence_index": 0, "sentence_index_neg": 3}, {"wf": "ОРЫНЫЛ,", "off_start": 8, "off_end": 15, "wtype": "word", "ana": [{"parts": "orɨnɨ-l", "gloss": "олень-PL", "gloss_index": "олень{orɨnɨ}-PL{l}-"}], "next_word": 2, "sentence_index": 1, "sentence_index_neg": 2}, {"wf": "ОРЫМӇЫЛДА", "off_start": 16, "off_end": 25, "wtype": "word", "ana": [{"parts": "orɨ-mŋɨ-lda", "gloss": "олень-AG.PROF-PL-ADD", "gloss_index": "олень{orɨ}-AG.PROF{mŋɨ}-PL{lda}-"}], "next_word": 3, "sentence_index": 2, "sentence_index_neg": 1}], "lang": 0, "para_alignment": [{"off_start": 0, "off_end": 25, "para_id": 5}]}, {"text": "Ояв там бисэкын орымӈылду туркувэтты диплыв ымудавыр вертолетыч.", "words": [{"wf": "Ояв", "off_start": 0, "off_end": 3, "wtype": "word", "ana": [{"parts": "oja-w", "gloss": "много-ACC", "gloss_index": "много{oja}-ACC{w}-"}], "next_word": 1, "sentence_index": 0, "sentence_index_neg": 8}, {"wf": "там", "off_start": 4, "off_end": 7, "wtype": "word", "ana": [{"parts": "tam", "gloss": "там", "gloss_index": "там{tam}-"}], "next_word": 2, "sentence_index": 1, "sentence_index_neg": 7}, {"wf": "бисэкын", "off_start": 8, "off_end": 15, "wtype": "word", "ana": [{"parts": "bi-sekɨn", "gloss": "быть-SIM", "gloss_index": "быть{bi}-SIM{sekɨn}-"}], "next_word": 3, "sentence_index": 2, "sentence_index_neg": 6}, {"wf": "орымӈылду", "off_start": 16, "off_end": 25, "wtype": "word", "ana": [{"parts": "orɨ-mŋɨ-l-du", "gloss": "олень-AG.PROF-PL-DAT", "gloss_index": "олень{orɨ}-AG.PROF{mŋɨ}-PL{l}-DAT{du}-"}], "next_word": 4, "sentence_index": 3, "sentence_index_neg": 5}, {"wf": "туркувэтты", "off_start": 26, "off_end": 36, "wtype": "word", "ana": [{"parts": "turku-wet-tɨ-∅", "gloss": "не.мочь-FREQ-NFUT-3PL", "gloss_index": "не.мочь{turku}-FREQ{wet}-NFUT{tɨ}-3PL{∅}-"}], "next_word": 5, "sentence_index": 4, "sentence_index_neg": 4}, {"wf": "диплыв", "off_start": 37, "off_end": 43, "wtype": "word", "ana": [{"parts": "d'iplɨ-w", "gloss": "еда-ACC", "gloss_index": "еда{d'iplɨ}-ACC{w}-"}], "next_word": 6, "sentence_index": 5, "sentence_index_neg": 3}, {"wf": "ымудавыр", "off_start": 44, "off_end": 52, "wtype": "word", "ana": [{"parts": "ɨm-u-da-wɨr", "gloss": "приходить-AD-PURP-1PL.INC", "gloss_index": "приходить{ɨm}-AD{u}-PURP{da}-1PL.INC{wɨr}-"}], "next_word": 7, "sentence_index": 6, "sentence_index_neg": 2}, {"wf": "вертолетыч.", "off_start": 53, "off_end": 64, "wtype": "word", "ana": [{"parts": "w'ertol'etɨ-č", "gloss": "вертолёт-INS", "gloss_index": "вертолёт{w'ertol'etɨ}-INS{č}-"}], "next_word": 8, "sentence_index": 7, "sentence_index_neg": 1}], "lang": 0, "para_alignment": [{"off_start": 0, "off_end": 64, "para_id": 6}]}, {"text": "Тэми нян орымӈыл улэдды орбур, селотыки нуддэ инив аю гэлэтми.", "words": [{"wf": "Тэми", "off_start": 0, "off_end": 4, "wtype": "word", "ana": [{"parts": "temi", "gloss": "поэтому", "gloss_index": "поэтому{temi}-"}], "next_word": 1, "sentence_index": 0, "sentence_index_neg": 10}, {"wf": "нян", "off_start": 5, "off_end": 8, "wtype": "word", "ana": [{"parts": "n'an", "gloss": "и", "gloss_index": "и{n'an}-"}], "next_word": 2, "sentence_index": 1, "sentence_index_neg": 9}, {"wf": "орымӈыл", "off_start": 9, "off_end": 16, "wtype": "word", "ana": [{"parts": "orɨ-mŋɨ-l", "gloss": "олень-AG.PROF-PL", "gloss_index": "олень{orɨ}-AG.PROF{mŋɨ}-PL{l}-"}], "next_word": 3, "sentence_index": 2, "sentence_index_neg": 8}, {"wf": "улэдды", "off_start": 17, "off_end": 23, "wtype": "word", "ana": [{"parts": "uled-dɨ-∅", "gloss": "оставить-PROG-NFUT-3PL", "gloss_index": "оставить{uled}-PROG{dɨ}-NFUT{∅}-"}], "next_word": 4, "sentence_index": 3, "sentence_index_neg": 7}, {"wf": "орбур,", "off_start": 24, "off_end": 30, "wtype": "word", "ana": [{"parts": "or-bur", "gloss": "олень-POSS.REFL.PL", "gloss_index": "олень{or}-POSS.REFL.PL{bur}-"}], "next_word": 5, "sentence_index": 4, "sentence_index_neg": 6}, {"wf": "селотыки", "off_start": 31, "off_end": 39, "wtype": "word", "ana": [{"parts": "s'elo-tɨki", "gloss": "село-DIR", "gloss_index": "село{s'elo}-DIR{tɨki}-"}], "next_word": 6, "sentence_index": 5, "sentence_index_neg": 5}, {"wf": "нуддэ", "off_start": 40, "off_end": 45, "wtype": "word", "ana": [{"parts": "nud-de-∅", "gloss": "кочевать-NFUT-3PL", "gloss_index": "кочевать{nud}-NFUT{de}-3PL{∅}-"}], "next_word": 7, "sentence_index": 6, "sentence_index_neg": 4}, {"wf": "инив", "off_start": 46, "off_end": 50, "wtype": "word", "ana": [{"parts": "ini-w", "gloss": "жизнь-ACC", "gloss_index": "жизнь{ini}-ACC{w}-"}], "next_word": 8, "sentence_index": 7, "sentence_index_neg": 3}, {"wf": "аю", "off_start": 51, "off_end": 53, "wtype": "word", "ana": [{"parts": "aj-u", "gloss": "хороший-ACC", "gloss_index": "хороший{aj}-ACC{u}-"}], "next_word": 9, "sentence_index": 8, "sentence_index_neg": 2}, {"wf": "гэлэтми.", "off_start": 54, "off_end": 62, "wtype": "word", "ana": [{"parts": "gelet-mi", "gloss": "искать-COND.SS", "gloss_index": "искать{gelet}-COND.SS{mi}-"}], "next_word": 10, "sentence_index": 9, "sentence_index_neg": 1}], "lang": 0, "para_alignment": [{"off_start": 0, "off_end": 62, "para_id": 7}]}, {"text": "Оявда тыкыр орылбы быритнэритын тачиннун.", "words": [{"wf": "Оявда", "off_start": 0, "off_end": 5, "wtype": "word", "ana": [{"parts": "oja-w-da", "gloss": "много-ACC-ADD", "gloss_index": "много{oja}-ACC{w}-ADD{da}-"}], "next_word": 1, "sentence_index": 0, "sentence_index_neg": 5}, {"wf": "тыкыр", "off_start": 6, "off_end": 11, "wtype": "word", "ana": [{"parts": "tikɨ-r", "gloss": "сейчас-ADJ.TIME", "gloss_index": "сейчас{tikɨ}-ADJ.TIME{r}-"}], "next_word": 2, "sentence_index": 1, "sentence_index_neg": 4}, {"wf": "орылбы", "off_start": 12, "off_end": 18, "wtype": "word", "ana": [{"parts": "orɨ-l-bɨ", "gloss": "олень-PL-ACC", "gloss_index": "олень{orɨ}-PL{l}-ACC{bɨ}-"}], "next_word": 3, "sentence_index": 2, "sentence_index_neg": 3}, {"wf": "быритнэритын", "off_start": 19, "off_end": 31, "wtype": "word", "ana": [{"parts": "bɨri-t-ne-ri-tɨn", "gloss": "потерять-PROG-MCP-PST-3PL", "gloss_index": "потерять{bɨri}-PROG{t}-MCP{ne}-PST{ri}-3PL{tɨn}-"}], "next_word": 4, "sentence_index": 3, "sentence_index_neg": 2}, {"wf": "тачиннун.", "off_start": 32, "off_end": 41, "wtype": "word", "ana": [{"parts": "ta-čin-nun", "gloss": "DEM.DIST-NMZ-COM", "gloss_index": "DEM.DIST{ta}-NMZ{čin}-COM{nun}-"}], "next_word": 5, "sentence_index": 4, "sentence_index_neg": 1}], "lang": 0, "para_alignment": [{"off_start": 0, "off_end": 41, "para_id": 8}]}, {"text": "Ольский райондула тунӈын хозяйстватын бисин, эдук тунӈэндук улаптын умэнты.", "words": [{"wf": "Ольский", "off_start": 0, "off_end": 7, "wtype": "word", "ana": [{"parts": "olskij", "gloss": "Ольский", "gloss_index": "Ольский{olskij}-"}], "next_word": 1, "sentence_index": 0, "sentence_index_neg": 9}, {"wf": "райондула", "off_start": 8, "off_end": 17, "wtype": "word", "ana": [{"parts": "rajon-dula", "gloss": "район-LOC", "gloss_index": "район{rajon}-LOC{dula}-"}], "next_word": 2, "sentence_index": 1, "sentence_index_neg": 8}, {"wf": "тунӈын", "off_start": 18, "off_end": 24, "wtype": "word", "ana": [{"parts": "tunŋɨn", "gloss": "5", "gloss_index": "5{tunŋɨn}-"}], "next_word": 3, "sentence_index": 2, "sentence_index_neg": 7}, {"wf": "хозяйстватын", "off_start": 25, "off_end": 37, "wtype": "word", "ana": [{"parts": "xoz'ajstwa-tɨn", "gloss": "хозяйство-POSS.3PL", "gloss_index": "хозяйство{xoz'ajstwa}-POSS.3PL{tɨn}-"}], "next_word": 4, "sentence_index": 3, "sentence_index_neg": 6}, {"wf": "бисин,", "off_start": 38, "off_end": 44, "wtype": "word", "ana": [{"parts": "bi-si-n", "gloss": "быть-PST-3SG", "gloss_index": "быть{bi}-PST{si}-3SG{n}-"}], "next_word": 5, "sentence_index": 4, "sentence_index_neg": 5}, {"wf": "эдук", "off_start": 45, "off_end": 49, "wtype": "word", "ana": [{"parts": "e-duk", "gloss": "DEM.PROX-ABL", "gloss_index": "DEM.PROX{e}-ABL{duk}-"}], "next_word": 6, "sentence_index": 5, "sentence_index_neg": 4}, {"wf": "тунӈэндук", "off_start": 50, "off_end": 59, "wtype": "word", "ana": [{"parts": "tunŋen-duk", "gloss": "5-ABL", "gloss_index": "5{tunŋen}-ABL{duk}-"}], "next_word": 7, "sentence_index": 6, "sentence_index_neg": 3}, {"wf": "улаптын", "off_start": 60, "off_end": 67, "wtype": "word", "ana": [{"parts": "ula-p-tɨ-n", "gloss": "оставить-MED-PST-3SG", "gloss_index": "оставить{ula}-MED{p}-PST{tɨ}-3SG{n}-"}], "next_word": 8, "sentence_index": 7, "sentence_index_neg": 2}, {"wf": "умэнты.", "off_start": 68, "off_end": 75, "wtype": "word", "ana": [{"parts": "umen-tɨ", "gloss": "1-ADD", "gloss_index": "1{umen}-ADD{tɨ}-"}], "next_word": 9, "sentence_index": 8, "sentence_index_neg": 1}], "lang": 0, "para_alignment": [{"off_start": 0, "off_end": 75, "para_id": 9}]}, {"text": "Умындулэттэ онычиси маниучидда эдэвыр бэритнэр орыӈылбур.", "words": [{"wf": "Умындулэттэ", "off_start": 0, "off_end": 11, "wtype": "word", "ana": [{"parts": "umɨn-dule-t-te", "gloss": "1-LOC-FOC-ADD", "gloss_index": "1{umɨn}-LOC{dule}-FOC{t}-ADD{te}-"}], "next_word": 1, "sentence_index": 0, "sentence_index_neg": 6}, {"wf": "онычиси", "off_start": 12, "off_end": 19, "wtype": "word", "ana": [{"parts": "onɨ-či-si", "gloss": "как-INS-EMPH", "gloss_index": "как{onɨ}-INS{či}-EMPH{si}-"}], "next_word": 2, "sentence_index": 1, "sentence_index_neg": 5}, {"wf": "маниучидда", "off_start": 20, "off_end": 30, "wtype": "word", "ana": [{"parts": "maniu-či-d-da-∅", "gloss": "стараться-RES-PROG-NFUT-3PL", "gloss_index": "стараться{maniu}-RES{či}-PROG{d}-NFUT{da}-3PL{∅}-"}], "next_word": 3, "sentence_index": 2, "sentence_index_neg": 4}, {"wf": "эдэвыр", "off_start": 31, "off_end": 37, "wtype": "word", "ana": [{"parts": "e-de-wɨr", "gloss": "NEG-PURP-POSS.REFL.PL", "gloss_index": "NEG{e}-PURP{de}-POSS.REFL.PL{wɨr}-"}], "next_word": 4, "sentence_index": 3, "sentence_index_neg": 3}, {"wf": "бэритнэр", "off_start": 38, "off_end": 46, "wtype": "word", "ana": [{"parts": "beri-t-ne-r", "gloss": "потерять-PROG-MCP-CVB.NEG", "gloss_index": "потерять{beri}-PROG{t}-MCP{ne}-CVB.NEG{r}-"}], "next_word": 5, "sentence_index": 4, "sentence_index_neg": 2}, {"wf": "орыӈылбур.", "off_start": 47, "off_end": 57, "wtype": "word", "ana": [{"parts": "orɨ-ŋi-l-bur", "gloss": "олень-AL-PL-POSS.REFL.PL", "gloss_index": "олень{orɨ}-AL{ŋi}-PL{l}-POSS.REFL.PL{bur}-"}], "next_word": 6, "sentence_index": 5, "sentence_index_neg": 1}], "lang": 0, "para_alignment": [{"off_start": 0, "off_end": 57, "para_id": 10}]}, {"text": "ДЭРПЭК ОРДУЛА - ИЛУС", "words": [{"wf": "ДЭРПЭК", "off_start": 0, "off_end": 6, "wtype": "word", "ana": [{"parts": "derpek", "gloss": "сосед", "gloss_index": "сосед{derpek}-"}], "next_word": 1, "sentence_index": 0, "sentence_index_neg": 3}, {"wf": "ОРДУЛА", "off_start": 7, "off_end": 13, "wtype": "word", "ana": [{"parts": "or-dula", "gloss": "олень-LOC", "gloss_index": "олень{or}-LOC{dula}-"}], "next_word": 2, "sentence_index": 1, "sentence_index_neg": 2}, {"wf": "ИЛУС", "off_start": 16, "off_end": 20, "wtype": "word", "ana": [{"parts": "ilus", "gloss": "беда", "gloss_index": "беда{ilus}-"}], "next_word": 3, "sentence_index": 2, "sentence_index_neg": 1}], "lang": 0, "para_alignment": [{"off_start": 0, "off_end": 20, "para_id": 11}]}, {"text": "Анадырьла кокэддэ орыныл Чукоткэлэ.", "words": [{"wf": "Анадырьла", "off_start": 0, "off_end": 9, "wtype": "word", "ana": [{"parts": "anadɨr'-la", "gloss": "Анадырь-LOC", "gloss_index": "Анадырь{anadɨr'}-LOC{la}-"}], "next_word": 1, "sentence_index": 0, "sentence_index_neg": 4}, {"wf": "кокэддэ", "off_start": 10, "off_end": 17, "wtype": "word", "ana": [{"parts": "koke-d-de-∅", "gloss": "умереть-PROG-NFUT-3PL", "gloss_index": "умереть{koke}-PROG{d}-NFUT{de}-3PL{∅}-"}], "next_word": 2, "sentence_index": 1, "sentence_index_neg": 3}, {"wf": "орыныл", "off_start": 18, "off_end": 24, "wtype": "word", "ana": [{"parts": "orɨnɨ-l", "gloss": "олень-PL", "gloss_index": "олень{orɨnɨ}-PL{l}-"}], "next_word": 3, "sentence_index": 2, "sentence_index_neg": 2}, {"wf": "Чукоткэлэ.", "off_start": 25, "off_end": 35, "wtype": "word", "ana": [{"parts": "čukotke-le", "gloss": "Чукотка-LOC", "gloss_index": "Чукотка{čukotke}-LOC{le}-"}], "next_word": 4, "sentence_index": 3, "sentence_index_neg": 1}], "lang": 0, "para_alignment": [{"off_start": 0, "off_end": 35, "para_id": 12}]}, {"text": "Оя энтэкэе.", "words": [{"wf": "Оя", "off_start": 0, "off_end": 2, "wtype": "word", "ana": [{"parts": "oja", "gloss": "много", "gloss_index": "много{oja}-"}], "next_word": 1, "sentence_index": 0, "sentence_index_neg": 2}, {"wf": "энтэкэе.", "off_start": 3, "off_end": 11, "wtype": "word", "ana": [{"parts": "ente-keje", "gloss": "очень-AUG", "gloss_index": "очень{ente}-AUG{keje}-"}], "next_word": 2, "sentence_index": 1, "sentence_index_neg": 1}], "lang": 0, "para_alignment": [{"off_start": 0, "off_end": 11, "para_id": 13}]}, {"text": "Туҕыни одыкын 3000 тысяча орын кокэрин.", "words": [{"wf": "Туҕыни", "off_start": 0, "off_end": 6, "wtype": "word", "ana": [{"parts": "tugɨni", "gloss": "зима", "gloss_index": "зима{tugɨni}-"}], "next_word": 1, "sentence_index": 0, "sentence_index_neg": 6}, {"wf": "одыкын", "off_start": 7, "off_end": 13, "wtype": "word", "ana": [{"parts": "odɨ-kɨn", "gloss": "стать-SIM", "gloss_index": "стать{odɨ}-SIM{kɨn}-"}], "next_word": 2, "sentence_index": 1, "sentence_index_neg": 5}, {"wf": "3000", "off_start": 14, "off_end": 18, "wtype": "word", "ana": [{"parts": "3000", "gloss": "3000", "gloss_index": "3000{3000}-"}], "next_word": 3, "sentence_index": 2, "sentence_index_neg": 4}, {"wf": "тысяча", "off_start": 19, "off_end": 25, "wtype": "word", "ana": [{"parts": "tɨs'ača", "gloss": "тысяча", "gloss_index": "тысяча{tɨs'ača}-"}], "next_word": 4, "sentence_index": 3, "sentence_index_neg": 3}, {"wf": "орын", "off_start": 26, "off_end": 30, "wtype": "word", "ana": [{"parts": "orɨn", "gloss": "олень", "gloss_index": "олень{orɨn}-"}], "next_word": 5, "sentence_index": 4, "sentence_index_neg": 2}, {"wf": "кокэрин.", "off_start": 31, "off_end": 39, "wtype": "word", "ana": [{"parts": "koke-ri-n", "gloss": "умереть-PST-3SG", "gloss_index": "умереть{koke}-PST{ri}-3SG{n}-"}], "next_word": 6, "sentence_index": 5, "sentence_index_neg": 1}], "lang": 0, "para_alignment": [{"off_start": 0, "off_end": 39, "para_id": 14}]}, {"text": "Оӈкадяк имынныдук, удындук букыс одыкын, орыныл туркуритэн диплэӈгэвыр бакры, тадуттэ эткэтитэн, димми.", "words": [{"wf": "Оӈкадяк", "off_start": 0, "off_end": 7, "wtype": "word", "ana": [{"parts": "Oŋka-d'ak", "gloss": "oŋkad'ak-n", "gloss_index": "oŋkad'ak{Oŋka}-n{d'ak}-"}], "next_word": 1, "sentence_index": 0, "sentence_index_neg": 12}, {"wf": "имынныдук,", "off_start": 8, "off_end": 18, "wtype": "word", "ana": [{"parts": "imɨnnɨ-duk", "gloss": "Notanalysed", "gloss_index": "Notanalysed{imɨnnɨ}-"}], "next_word": 2, "sentence_index": 1, "sentence_index_neg": 11}, {"wf": "удындук", "off_start": 19, "off_end": 26, "wtype": "word", "ana": [{"parts": "udɨn-duk", "gloss": "ud-v-tr-adj-num-nmz.abst-abl", "gloss_index": "ud{udɨn}-v{duk}-"}], "next_word": 3, "sentence_index": 2, "sentence_index_neg": 10}, {"wf": "букыс", "off_start": 27, "off_end": 32, "wtype": "word", "ana": [{"parts": "bukɨs", "gloss": "Notanalysed", "gloss_index": "Notanalysed{bukɨs}-"}], "next_word": 4, "sentence_index": 3, "sentence_index_neg": 9}, {"wf": "одыкын,", "off_start": 33, "off_end": 40, "wtype": "word", "ana": [{"parts": "odɨ-kɨn", "gloss": "od-v-adj-num-пастись-NMZ.PLACE", "gloss_index": "od{odɨ}-v{kɨn}-"}], "next_word": 5, "sentence_index": 4, "sentence_index_neg": 8}, {"wf": "орыныл", "off_start": 41, "off_end": 47, "wtype": "word", "ana": [{"parts": "orɨni-l", "gloss": "снег-ABL", "gloss_index": "снег{orɨni}-ABL{l}-"}], "next_word": 6, "sentence_index": 5, "sentence_index_neg": 7}, {"wf": "туркуритэн", "off_start": 48, "off_end": 58, "wtype": "word", "ana": [{"parts": "turku-ri-ten", "gloss": "дождь-ABL", "gloss_index": "дождь{turku}-ABL{ri}-"}], "next_word": 7, "sentence_index": 6, "sentence_index_neg": 6}, {"wf": "диплэӈгэвыр", "off_start": 59, "off_end": 70, "wtype": "word", "ana": [{"parts": "d'iple-ŋ-ge-wɨr", "gloss": "лёд", "gloss_index": "лёд{d'iple}-"}], "next_word": 8, "sentence_index": 7, "sentence_index_neg": 5}, {"wf": "бакры,", "off_start": 71, "off_end": 77, "wtype": "word", "ana": [{"parts": "bak-rɨ", "gloss": "стать-SIM", "gloss_index": "стать{bak}-SIM{rɨ}-"}], "next_word": 9, "sentence_index": 8, "sentence_index_neg": 4}, {"wf": "тадуттэ", "off_start": 78, "off_end": 85, "wtype": "word", "ana": [{"parts": "ta-dut-te", "gloss": "олень-PL", "gloss_index": "олень{ta}-PL{dut}-"}], "next_word": 10, "sentence_index": 9, "sentence_index_neg": 3}, {"wf": "эткэтитэн,", "off_start": 86, "off_end": 96, "wtype": "word", "ana": [{"parts": "etke-ti-ten", "gloss": "не.мочь-PST-3PL", "gloss_index": "не.мочь{etke}-PST{ti}-3PL{ten}-"}], "next_word": 11, "sentence_index": 10, "sentence_index_neg": 2}, {"wf": "димми.", "off_start": 97, "off_end": 103, "wtype": "word", "ana": [{"parts": "d'im-mi", "gloss": "еда-AL-DST-POSS.REFL.PL", "gloss_index": "еда{d'im}-AL{mi}-"}], "next_word": 12, "sentence_index": 11, "sentence_index_neg": 1}], "lang": 0, "para_alignment": [{"off_start": 0, "off_end": 103, "para_id": 15}]}, {"text": "Орымӈыл бутэнилбэ маватэ, улаптилба илбэритын тэҕэски тундрэтки, илэккы аччи букэс.", "words": [{"wf": "Орымӈыл", "off_start": 0, "off_end": 7, "wtype": "word", "ana": [{"parts": "orɨ-mŋɨ-l", "gloss": "олень-AG.PROF-PL", "gloss_index": "олень{orɨ}-AG.PROF{mŋɨ}-PL{l}-"}], "next_word": 1, "sentence_index": 0, "sentence_index_neg": 10}, {"wf": "бутэнилбэ", "off_start": 8, "off_end": 17, "wtype": "word", "ana": [{"parts": "buteni-l-be", "gloss": "больной-PL-ACC", "gloss_index": "больной{buteni}-PL{l}-ACC{be}-"}], "next_word": 2, "sentence_index": 1, "sentence_index_neg": 9}, {"wf": "маватэ,", "off_start": 18, "off_end": 25, "wtype": "word", "ana": [{"parts": "ma-wa-ta-∅", "gloss": "убить-FREQ-NFUT-3PL", "gloss_index": "убить{ma}-FREQ{wa}-NFUT{ta}-3PL{∅}-"}], "next_word": 3, "sentence_index": 2, "sentence_index_neg": 8}, {"wf": "улаптилба", "off_start": 26, "off_end": 35, "wtype": "word", "ana": [{"parts": "ulap-ti-l-ba", "gloss": "оставаться-PTC.NFUT-PL-ACC", "gloss_index": "оставаться{ulap}-PTC.NFUT{ti}-PL{l}-ACC{ba}-"}], "next_word": 4, "sentence_index": 3, "sentence_index_neg": 7}, {"wf": "илбэритын", "off_start": 36, "off_end": 45, "wtype": "word", "ana": [{"parts": "ilbe-ri-tən", "gloss": "гнать-PST-3PL", "gloss_index": "гнать{ilbe}-PST{ri}-3PL{tən}-"}], "next_word": 5, "sentence_index": 4, "sentence_index_neg": 6}, {"wf": "тэҕэски", "off_start": 46, "off_end": 53, "wtype": "word", "ana": [{"parts": "tege-ski", "gloss": "даль-ADV.DIR", "gloss_index": "даль{tege}-ADV.DIR{ski}-"}], "next_word": 6, "sentence_index": 5, "sentence_index_neg": 5}, {"wf": "тундрэтки,", "off_start": 54, "off_end": 64, "wtype": "word", "ana": [{"parts": "tundra-tki", "gloss": "тундра-DIR", "gloss_index": "тундра{tundra}-DIR{tki}-"}], "next_word": 7, "sentence_index": 6, "sentence_index_neg": 4}, {"wf": "илэккы", "off_start": 65, "off_end": 71, "wtype": "word", "ana": [{"parts": "i-le-kkɨ", "gloss": "DEM.Q-LOC-EMPH", "gloss_index": "DEM.Q{i}-LOC{le}-EMPH{kkɨ}-"}], "next_word": 8, "sentence_index": 7, "sentence_index_neg": 3}, {"wf": "аччи", "off_start": 72, "off_end": 76, "wtype": "word", "ana": [{"parts": "ačči", "gloss": "NEG.PRED", "gloss_index": "NEG.PRED{ačči}-"}], "next_word": 9, "sentence_index": 8, "sentence_index_neg": 2}, {"wf": "букэс.", "off_start": 77, "off_end": 83, "wtype": "word", "ana": [{"parts": "bukes", "gloss": "лёд", "gloss_index": "лёд{bukes}-"}], "next_word": 10, "sentence_index": 9, "sentence_index_neg": 1}], "lang": 0, "para_alignment": [{"off_start": 0, "off_end": 83, "para_id": 16}]}, {"text": "Орын кокэддын энтэкэе.", "words": [{"wf": "Орын", "off_start": 0, "off_end": 4, "wtype": "word", "ana": [{"parts": "orɨn", "gloss": "олень", "gloss_index": "олень{orɨn}-"}], "next_word": 1, "sentence_index": 0, "sentence_index_neg": 3}, {"wf": "кокэддын", "off_start": 5, "off_end": 13, "wtype": "word", "ana": [{"parts": "koke-dɨ-n", "gloss": "умереть-PROG-PST-3SG", "gloss_index": "умереть{koke}-PROG{dɨ}-PST{n}-"}], "next_word": 2, "sentence_index": 1, "sentence_index_neg": 2}, {"wf": "энтэкэе.", "off_start": 14, "off_end": 22, "wtype": "word", "ana": [{"parts": "ente-keje", "gloss": "очень-AUG", "gloss_index": "очень{ente}-AUG{keje}-"}], "next_word": 3, "sentence_index": 2, "sentence_index_neg": 1}], "lang": 0, "para_alignment": [{"off_start": 0, "off_end": 22, "para_id": 17}]}, {"text": "Абыл одиллэн.", "words": [{"wf": "Абыл", "off_start": 0, "off_end": 4, "wtype": "word", "ana": [{"parts": "abɨl", "gloss": "мало", "gloss_index": "мало{abɨl}-"}], "next_word": 1, "sentence_index": 0, "sentence_index_neg": 2}, {"wf": "одиллэн.", "off_start": 5, "off_end": 13, "wtype": "word", "ana": [{"parts": "oďi-l-le-n", "gloss": "стать-INCH-NFUT-3SG", "gloss_index": "стать{oďi}-INCH{l}-NFUT{le}-3SG{n}-"}], "next_word": 2, "sentence_index": 1, "sentence_index_neg": 1}], "lang": 0, "para_alignment": [{"off_start": 0, "off_end": 13, "para_id": 18}]}, {"text": "И о жизни оленеводов.", "words": [{"wf": "И", "off_start": 0, "off_end": 1, "wtype": "word", "next_word": 1, "sentence_index": 0, "sentence_index_neg": 4}, {"wf": "о", "off_start": 2, "off_end": 3, "wtype": "word", "next_word": 2, "sentence_index": 1, "sentence_index_neg": 3}, {"wf": "жизни", "off_start": 4, "off_end": 9, "wtype": "word", "next_word": 3, "sentence_index": 2, "sentence_index_neg": 2}, {"wf": "оленеводов.", "off_start": 10, "off_end": 21, "wtype": "word", "next_word": 4, "sentence_index": 3, "sentence_index_neg": 1}], "lang": 1, "para_alignment": [{"off_start": 0, "off_end": 21, "para_id": 0}]}, {"text": "Сейчас жизнь стала трудной в табуне.", "words": [{"wf": "Сейчас", "off_start": 0, "off_end": 6, "wtype": "word", "next_word": 1, "sentence_index": 0, "sentence_index_neg": 6}, {"wf": "жизнь", "off_start": 7, "off_end": 12, "wtype": "word", "next_word": 2, "sentence_index": 1, "sentence_index_neg": 5}, {"wf": "стала", "off_start": 13, "off_end": 18, "wtype": "word", "next_word": 3, "sentence_index": 2, "sentence_index_neg": 4}, {"wf": "трудной", "off_start": 19, "off_end": 26, "wtype": "word", "next_word": 4, "sentence_index": 3, "sentence_index_neg": 3}, {"wf": "в", "off_start": 27, "off_end": 28, "wtype": "word", "next_word": 5, "sentence_index": 4, "sentence_index_neg": 2}, {"wf": "табуне.", "off_start": 29, "off_end": 36, "wtype": "word", "next_word": 6, "sentence_index": 5, "sentence_index_neg": 1}], "lang": 1, "para_alignment": [{"off_start": 0, "off_end": 36, "para_id": 1}]}, {"text": "В нашем районе плохо в табуне, в Анавгае стало плохо.", "words": [{"wf": "В", "off_start": 0, "off_end": 1, "wtype": "word", "next_word": 1, "sentence_index": 0, "sentence_index_neg": 10}, {"wf": "нашем", "off_start": 2, "off_end": 7, "wtype": "word", "next_word": 2, "sentence_index": 1, "sentence_index_neg": 9}, {"wf": "районе", "off_start": 8, "off_end": 14, "wtype": "word", "next_word": 3, "sentence_index": 2, "sentence_index_neg": 8}, {"wf": "плохо", "off_start": 15, "off_end": 20, "wtype": "word", "next_word": 4, "sentence_index": 3, "sentence_index_neg": 7}, {"wf": "в", "off_start": 21, "off_end": 22, "wtype": "word", "next_word": 5, "sentence_index": 4, "sentence_index_neg": 6}, {"wf": "табуне,", "off_start": 23, "off_end": 30, "wtype": "word", "next_word": 6, "sentence_index": 5, "sentence_index_neg": 5}, {"wf": "в", "off_start": 31, "off_end": 32, "wtype": "word", "next_word": 7, "sentence_index": 6, "sentence_index_neg": 4}, {"wf": "Анавгае", "off_start": 33, "off_end": 40, "wtype": "word", "next_word": 8, "sentence_index": 7, "sentence_index_neg": 3}, {"wf": "стало", "off_start": 41, "off_end": 46, "wtype": "word", "next_word": 9, "sentence_index": 8, "sentence_index_neg": 2}, {"wf": "плохо.", "off_start": 47, "off_end": 53, "wtype": "word", "next_word": 10, "sentence_index": 9, "sentence_index_neg": 1}], "lang": 1, "para_alignment": [{"off_start": 0, "off_end": 53, "para_id": 2}]}, {"text": "Вот, как живут неместные оленеводы из Тигильской районной газеты «Панорама».", "words": [{"wf": "Вот,", "off_start": 0, "off_end": 4, "wtype": "word", "next_word": 1, "sentence_index": 0, "sentence_index_neg": 10}, {"wf": "как", "off_start": 5, "off_end": 8, "wtype": "word", "next_word": 2, "sentence_index": 1, "sentence_index_neg": 9}, {"wf": "живут", "off_start": 9, "off_end": 14, "wtype": "word", "next_word": 3, "sentence_index": 2, "sentence_index_neg": 8}, {"wf": "неместные", "off_start": 15, "off_end": 24, "wtype": "word", "next_word": 4, "sentence_index": 3, "sentence_index_neg": 7}, {"wf": "оленеводы", "off_start": 25, "off_end": 34, "wtype": "word", "next_word": 5, "sentence_index": 4, "sentence_index_neg": 6}, {"wf": "из", "off_start": 35, "off_end": 37, "wtype": "word", "next_word": 6, "sentence_index": 5, "sentence_index_neg": 5}, {"wf": "Тигильской", "off_start": 38, "off_end": 48, "wtype": "word", "next_word": 7, "sentence_index": 6, "sentence_index_neg": 4}, {"wf": "районной", "off_start": 49, "off_end": 57, "wtype": "word", "next_word": 8, "sentence_index": 7, "sentence_index_neg": 3}, {"wf": "газеты", "off_start": 58, "off_end": 64, "wtype": "word", "next_word": 9, "sentence_index": 8, "sentence_index_neg": 2}, {"wf": "«Панорама».", "off_start": 65, "off_end": 76, "wtype": "word", "next_word": 10, "sentence_index": 9, "sentence_index_neg": 1}], "lang": 1, "para_alignment": [{"off_start": 0, "off_end": 76, "para_id": 3}]}, {"text": "Отсюда мы поймём, как работают в Магаданской области и на Чукотке.", "words": [{"wf": "Отсюда", "off_start": 0, "off_end": 6, "wtype": "word", "next_word": 1, "sentence_index": 0, "sentence_index_neg": 11}, {"wf": "мы", "off_start": 7, "off_end": 9, "wtype": "word", "next_word": 2, "sentence_index": 1, "sentence_index_neg": 10}, {"wf": "поймём,", "off_start": 10, "off_end": 17, "wtype": "word", "next_word": 3, "sentence_index": 2, "sentence_index_neg": 9}, {"wf": "как", "off_start": 18, "off_end": 21, "wtype": "word", "next_word": 4, "sentence_index": 3, "sentence_index_neg": 8}, {"wf": "работают", "off_start": 22, "off_end": 30, "wtype": "word", "next_word": 5, "sentence_index": 4, "sentence_index_neg": 7}, {"wf": "в", "off_start": 31, "off_end": 32, "wtype": "word", "next_word": 6, "sentence_index": 5, "sentence_index_neg": 6}, {"wf": "Магаданской", "off_start": 33, "off_end": 44, "wtype": "word", "next_word": 7, "sentence_index": 6, "sentence_index_neg": 5}, {"wf": "области", "off_start": 45, "off_end": 52, "wtype": "word", "next_word": 8, "sentence_index": 7, "sentence_index_neg": 4}, {"wf": "и", "off_start": 53, "off_end": 54, "wtype": "word", "next_word": 9, "sentence_index": 8, "sentence_index_neg": 3}, {"wf": "на", "off_start": 55, "off_end": 57, "wtype": "word", "next_word": 10, "sentence_index": 9, "sentence_index_neg": 2}, {"wf": "Чукотке.", "off_start": 58, "off_end": 66, "wtype": "word", "next_word": 11, "sentence_index": 10, "sentence_index_neg": 1}], "lang": 1, "para_alignment": [{"off_start": 0, "off_end": 66, "para_id": 4}]}, {"text": "Убежали олени и оленеводы.", "words": [{"wf": "Убежали", "off_start": 0, "off_end": 7, "wtype": "word", "next_word": 1, "sentence_index": 0, "sentence_index_neg": 4}, {"wf": "олени", "off_start": 8, "off_end": 13, "wtype": "word", "next_word": 2, "sentence_index": 1, "sentence_index_neg": 3}, {"wf": "и", "off_start": 14, "off_end": 15, "wtype": "word", "next_word": 3, "sentence_index": 2, "sentence_index_neg": 2}, {"wf": "оленеводы.", "off_start": 16, "off_end": 26, "wtype": "word", "next_word": 4, "sentence_index": 3, "sentence_index_neg": 1}], "lang": 1, "para_alignment": [{"off_start": 0, "off_end": 26, "para_id": 5}]}, {"text": "Много там было оленеводов, не удавалось привезти еду вертолётом.", "words": [{"wf": "Много", "off_start": 0, "off_end": 5, "wtype": "word", "next_word": 1, "sentence_index": 0, "sentence_index_neg": 9}, {"wf": "там", "off_start": 6, "off_end": 9, "wtype": "word", "next_word": 2, "sentence_index": 1, "sentence_index_neg": 8}, {"wf": "было", "off_start": 10, "off_end": 14, "wtype": "word", "next_word": 3, "sentence_index": 2, "sentence_index_neg": 7}, {"wf": "оленеводов,", "off_start": 15, "off_end": 26, "wtype": "word", "next_word": 4, "sentence_index": 3, "sentence_index_neg": 6}, {"wf": "не", "off_start": 27, "off_end": 29, "wtype": "word", "next_word": 5, "sentence_index": 4, "sentence_index_neg": 5}, {"wf": "удавалось", "off_start": 30, "off_end": 39, "wtype": "word", "next_word": 6, "sentence_index": 5, "sentence_index_neg": 4}, {"wf": "привезти", "off_start": 40, "off_end": 48, "wtype": "word", "next_word": 7, "sentence_index": 6, "sentence_index_neg": 3}, {"wf": "еду", "off_start": 49, "off_end": 52, "wtype": "word", "next_word": 8, "sentence_index": 7, "sentence_index_neg": 2}, {"wf": "вертолётом.", "off_start": 53, "off_end": 64, "wtype": "word", "next_word": 9, "sentence_index": 8, "sentence_index_neg": 1}], "lang": 1, "para_alignment": [{"off_start": 0, "off_end": 64, "para_id": 6}]}, {"text": "Поэтому оленеводы и покидали своих оленей и бежали в село в поисках хорошей жизни.", "words": [{"wf": "Поэтому", "off_start": 0, "off_end": 7, "wtype": "word", "next_word": 1, "sentence_index": 0, "sentence_index_neg": 14}, {"wf": "оленеводы", "off_start": 8, "off_end": 17, "wtype": "word", "next_word": 2, "sentence_index": 1, "sentence_index_neg": 13}, {"wf": "и", "off_start": 18, "off_end": 19, "wtype": "word", "next_word": 3, "sentence_index": 2, "sentence_index_neg": 12}, {"wf": "покидали", "off_start": 20, "off_end": 28, "wtype": "word", "next_word": 4, "sentence_index": 3, "sentence_index_neg": 11}, {"wf": "своих", "off_start": 29, "off_end": 34, "wtype": "word", "next_word": 5, "sentence_index": 4, "sentence_index_neg": 10}, {"wf": "оленей", "off_start": 35, "off_end": 41, "wtype": "word", "next_word": 6, "sentence_index": 5, "sentence_index_neg": 9}, {"wf": "и", "off_start": 42, "off_end": 43, "wtype": "word", "next_word": 7, "sentence_index": 6, "sentence_index_neg": 8}, {"wf": "бежали", "off_start": 44, "off_end": 50, "wtype": "word", "next_word": 8, "sentence_index": 7, "sentence_index_neg": 7}, {"wf": "в", "off_start": 51, "off_end": 52, "wtype": "word", "next_word": 9, "sentence_index": 8, "sentence_index_neg": 6}, {"wf": "село", "off_start": 53, "off_end": 57, "wtype": "word", "next_word": 10, "sentence_index": 9, "sentence_index_neg": 5}, {"wf": "в", "off_start": 58, "off_end": 59, "wtype": "word", "next_word": 11, "sentence_index": 10, "sentence_index_neg": 4}, {"wf": "поисках", "off_start": 60, "off_end": 67, "wtype": "word", "next_word": 12, "sentence_index": 11, "sentence_index_neg": 3}, {"wf": "хорошей", "off_start": 68, "off_end": 75, "wtype": "word", "next_word": 13, "sentence_index": 12, "sentence_index_neg": 2}, {"wf": "жизни.", "off_start": 76, "off_end": 82, "wtype": "word", "next_word": 14, "sentence_index": 13, "sentence_index_neg": 1}], "lang": 1, "para_alignment": [{"off_start": 0, "off_end": 82, "para_id": 7}]}, {"text": "В настоящее время большая часть поголовья утеряна безвозвратно.", "words": [{"wf": "В", "off_start": 0, "off_end": 1, "wtype": "word", "next_word": 1, "sentence_index": 0, "sentence_index_neg": 8}, {"wf": "настоящее", "off_start": 2, "off_end": 11, "wtype": "word", "next_word": 2, "sentence_index": 1, "sentence_index_neg": 7}, {"wf": "время", "off_start": 12, "off_end": 17, "wtype": "word", "next_word": 3, "sentence_index": 2, "sentence_index_neg": 6}, {"wf": "большая", "off_start": 18, "off_end": 25, "wtype": "word", "next_word": 4, "sentence_index": 3, "sentence_index_neg": 5}, {"wf": "часть", "off_start": 26, "off_end": 31, "wtype": "word", "next_word": 5, "sentence_index": 4, "sentence_index_neg": 4}, {"wf": "поголовья", "off_start": 32, "off_end": 41, "wtype": "word", "next_word": 6, "sentence_index": 5, "sentence_index_neg": 3}, {"wf": "утеряна", "off_start": 42, "off_end": 49, "wtype": "word", "next_word": 7, "sentence_index": 6, "sentence_index_neg": 2}, {"wf": "безвозвратно.", "off_start": 50, "off_end": 63, "wtype": "word", "next_word": 8, "sentence_index": 7, "sentence_index_neg": 1}], "lang": 1, "para_alignment": [{"off_start": 0, "off_end": 63, "para_id": 8}]}, {"text": "В Ольском районе 5 хозяйств было, из этих пяти осталось одно.", "words": [{"wf": "В", "off_start": 0, "off_end": 1, "wtype": "word", "next_word": 1, "sentence_index": 0, "sentence_index_neg": 11}, {"wf": "Ольском", "off_start": 2, "off_end": 9, "wtype": "word", "next_word": 2, "sentence_index": 1, "sentence_index_neg": 10}, {"wf": "районе", "off_start": 10, "off_end": 16, "wtype": "word", "next_word": 3, "sentence_index": 2, "sentence_index_neg": 9}, {"wf": "5", "off_start": 17, "off_end": 18, "wtype": "word", "next_word": 4, "sentence_index": 3, "sentence_index_neg": 8}, {"wf": "хозяйств", "off_start": 19, "off_end": 27, "wtype": "word", "next_word": 5, "sentence_index": 4, "sentence_index_neg": 7}, {"wf": "было,", "off_start": 28, "off_end": 33, "wtype": "word", "next_word": 6, "sentence_index": 5, "sentence_index_neg": 6}, {"wf": "из", "off_start": 34, "off_end": 36, "wtype": "word", "next_word": 7, "sentence_index": 6, "sentence_index_neg": 5}, {"wf": "этих", "off_start": 37, "off_end": 41, "wtype": "word", "next_word": 8, "sentence_index": 7, "sentence_index_neg": 4}, {"wf": "пяти", "off_start": 42, "off_end": 46, "wtype": "word", "next_word": 9, "sentence_index": 8, "sentence_index_neg": 3}, {"wf": "осталось", "off_start": 47, "off_end": 55, "wtype": "word", "next_word": 10, "sentence_index": 9, "sentence_index_neg": 2}, {"wf": "одно.", "off_start": 56, "off_end": 61, "wtype": "word", "next_word": 11, "sentence_index": 10, "sentence_index_neg": 1}], "lang": 1, "para_alignment": [{"off_start": 0, "off_end": 61, "para_id": 9}]}, {"text": "В одном только старались, чтобы не потерять оленей.", "words": [{"wf": "В", "off_start": 0, "off_end": 1, "wtype": "word", "next_word": 1, "sentence_index": 0, "sentence_index_neg": 8}, {"wf": "одном", "off_start": 2, "off_end": 7, "wtype": "word", "next_word": 2, "sentence_index": 1, "sentence_index_neg": 7}, {"wf": "только", "off_start": 8, "off_end": 14, "wtype": "word", "next_word": 3, "sentence_index": 2, "sentence_index_neg": 6}, {"wf": "старались,", "off_start": 15, "off_end": 25, "wtype": "word", "next_word": 4, "sentence_index": 3, "sentence_index_neg": 5}, {"wf": "чтобы", "off_start": 26, "off_end": 31, "wtype": "word", "next_word": 5, "sentence_index": 4, "sentence_index_neg": 4}, {"wf": "не", "off_start": 32, "off_end": 34, "wtype": "word", "next_word": 6, "sentence_index": 5, "sentence_index_neg": 3}, {"wf": "потерять", "off_start": 35, "off_end": 43, "wtype": "word", "next_word": 7, "sentence_index": 6, "sentence_index_neg": 2}, {"wf": "оленей.", "off_start": 44, "off_end": 51, "wtype": "word", "next_word": 8, "sentence_index": 7, "sentence_index_neg": 1}], "lang": 1, "para_alignment": [{"off_start": 0, "off_end": 51, "para_id": 10}]}, {"text": "В соседнем табуне беда.", "words": [{"wf": "В", "off_start": 0, "off_end": 1, "wtype": "word", "next_word": 1, "sentence_index": 0, "sentence_index_neg": 4}, {"wf": "соседнем", "off_start": 2, "off_end": 10, "wtype": "word", "next_word": 2, "sentence_index": 1, "sentence_index_neg": 3}, {"wf": "табуне", "off_start": 11, "off_end": 17, "wtype": "word", "next_word": 3, "sentence_index": 2, "sentence_index_neg": 2}, {"wf": "беда.", "off_start": 18, "off_end": 23, "wtype": "word", "next_word": 4, "sentence_index": 3, "sentence_index_neg": 1}], "lang": 1, "para_alignment": [{"off_start": 0, "off_end": 23, "para_id": 11}]}, {"text": "В Анадыре умирают олени на Чукотке.", "words": [{"wf": "В", "off_start": 0, "off_end": 1, "wtype": "word", "next_word": 1, "sentence_index": 0, "sentence_index_neg": 6}, {"wf": "Анадыре", "off_start": 2, "off_end": 9, "wtype": "word", "next_word": 2, "sentence_index": 1, "sentence_index_neg": 5}, {"wf": "умирают", "off_start": 10, "off_end": 17, "wtype": "word", "next_word": 3, "sentence_index": 2, "sentence_index_neg": 4}, {"wf": "олени", "off_start": 18, "off_end": 23, "wtype": "word", "next_word": 4, "sentence_index": 3, "sentence_index_neg": 3}, {"wf": "на", "off_start": 24, "off_end": 26, "wtype": "word", "next_word": 5, "sentence_index": 4, "sentence_index_neg": 2}, {"wf": "Чукотке.", "off_start": 27, "off_end": 35, "wtype": "word", "next_word": 6, "sentence_index": 5, "sentence_index_neg": 1}], "lang": 1, "para_alignment": [{"off_start": 0, "off_end": 35, "para_id": 12}]}, {"text": "Много\tочень.", "words": [{"wf": "Много", "off_start": 0, "off_end": 5, "wtype": "word", "next_word": 1, "sentence_index": 0, "sentence_index_neg": 2}, {"wf": "очень.", "off_start": 6, "off_end": 12, "wtype": "word", "next_word": 2, "sentence_index": 1, "sentence_index_neg": 1}], "lang": 1, "para_alignment": [{"off_start": 0, "off_end": 12, "para_id": 13}]}, {"text": "Когда зима наступила, 3 тысячи оленей умерло.", "words": [{"wf": "Когда", "off_start": 0, "off_end": 5, "wtype": "word", "next_word": 1, "sentence_index": 0, "sentence_index_neg": 7}, {"wf": "зима", "off_start": 6, "off_end": 10, "wtype": "word", "next_word": 2, "sentence_index": 1, "sentence_index_neg": 6}, {"wf": "наступила,", "off_start": 11, "off_end": 21, "wtype": "word", "next_word": 3, "sentence_index": 2, "sentence_index_neg": 5}, {"wf": "3", "off_start": 22, "off_end": 23, "wtype": "word", "next_word": 4, "sentence_index": 3, "sentence_index_neg": 4}, {"wf": "тысячи", "off_start": 24, "off_end": 30, "wtype": "word", "next_word": 5, "sentence_index": 4, "sentence_index_neg": 3}, {"wf": "оленей", "off_start": 31, "off_end": 37, "wtype": "word", "next_word": 6, "sentence_index": 5, "sentence_index_neg": 2}, {"wf": "умерло.", "off_start": 38, "off_end": 45, "wtype": "word", "next_word": 7, "sentence_index": 6, "sentence_index_neg": 1}], "lang": 1, "para_alignment": [{"off_start": 0, "off_end": 45, "para_id": 14}]}, {"text": "Пастбища от снега, и дождя, становятся ледяными, олени не могут найти еду, падают от голода.", "words": [{"wf": "Пастбища", "off_start": 0, "off_end": 8, "wtype": "word", "next_word": 1, "sentence_index": 0, "sentence_index_neg": 15}, {"wf": "от", "off_start": 9, "off_end": 11, "wtype": "word", "next_word": 2, "sentence_index": 1, "sentence_index_neg": 14}, {"wf": "снега,", "off_start": 12, "off_end": 18, "wtype": "word", "next_word": 3, "sentence_index": 2, "sentence_index_neg": 13}, {"wf": "и", "off_start": 19, "off_end": 20, "wtype": "word", "next_word": 4, "sentence_index": 3, "sentence_index_neg": 12}, {"wf": "дождя,", "off_start": 21, "off_end": 27, "wtype": "word", "next_word": 5, "sentence_index": 4, "sentence_index_neg": 11}, {"wf": "становятся", "off_start": 28, "off_end": 38, "wtype": "word", "next_word": 6, "sentence_index": 5, "sentence_index_neg": 10}, {"wf": "ледяными,", "off_start": 39, "off_end": 48, "wtype": "word", "next_word": 7, "sentence_index": 6, "sentence_index_neg": 9}, {"wf": "олени", "off_start": 49, "off_end": 54, "wtype": "word", "next_word": 8, "sentence_index": 7, "sentence_index_neg": 8}, {"wf": "не", "off_start": 55, "off_end": 57, "wtype": "word", "next_word": 9, "sentence_index": 8, "sentence_index_neg": 7}, {"wf": "могут", "off_start": 58, "off_end": 63, "wtype": "word", "next_word": 10, "sentence_index": 9, "sentence_index_neg": 6}, {"wf": "найти", "off_start": 64, "off_end": 69, "wtype": "word", "next_word": 11, "sentence_index": 10, "sentence_index_neg": 5}, {"wf": "еду,", "off_start": 70, "off_end": 74, "wtype": "word", "next_word": 12, "sentence_index": 11, "sentence_index_neg": 4}, {"wf": "падают", "off_start": 75, "off_end": 81, "wtype": "word", "next_word": 13, "sentence_index": 12, "sentence_index_neg": 3}, {"wf": "от", "off_start": 82, "off_end": 84, "wtype": "word", "next_word": 14, "sentence_index": 13, "sentence_index_neg": 2}, {"wf": "голода.", "off_start": 85, "off_end": 92, "wtype": "word", "next_word": 15, "sentence_index": 14, "sentence_index_neg": 1}], "lang": 1, "para_alignment": [{"off_start": 0, "off_end": 92, "para_id": 15}]}, {"text": "Оленеводы забивают больных, остальных отгоняют далеко в тундру, где нет льда.", "words": [{"wf": "Оленеводы", "off_start": 0, "off_end": 9, "wtype": "word", "next_word": 1, "sentence_index": 0, "sentence_index_neg": 11}, {"wf": "забивают", "off_start": 10, "off_end": 18, "wtype": "word", "next_word": 2, "sentence_index": 1, "sentence_index_neg": 10}, {"wf": "больных,", "off_start": 19, "off_end": 27, "wtype": "word", "next_word": 3, "sentence_index": 2, "sentence_index_neg": 9}, {"wf": "остальных", "off_start": 28, "off_end": 37, "wtype": "word", "next_word": 4, "sentence_index": 3, "sentence_index_neg": 8}, {"wf": "отгоняют", "off_start": 38, "off_end": 46, "wtype": "word", "next_word": 5, "sentence_index": 4, "sentence_index_neg": 7}, {"wf": "далеко", "off_start": 47, "off_end": 53, "wtype": "word", "next_word": 6, "sentence_index": 5, "sentence_index_neg": 6}, {"wf": "в", "off_start": 54, "off_end": 55, "wtype": "word", "next_word": 7, "sentence_index": 6, "sentence_index_neg": 5}, {"wf": "тундру,", "off_start": 56, "off_end": 63, "wtype": "word", "next_word": 8, "sentence_index": 7, "sentence_index_neg": 4}, {"wf": "где", "off_start": 64, "off_end": 67, "wtype": "word", "next_word": 9, "sentence_index": 8, "sentence_index_neg": 3}, {"wf": "нет", "off_start": 68, "off_end": 71, "wtype": "word", "next_word": 10, "sentence_index": 9, "sentence_index_neg": 2}, {"wf": "льда.", "off_start": 72, "off_end": 77, "wtype": "word", "next_word": 11, "sentence_index": 10, "sentence_index_neg": 1}], "lang": 1, "para_alignment": [{"off_start": 0, "off_end": 77, "para_id": 16}]}, {"text": "Олень умирал очень.", "words": [{"wf": "Олень", "off_start": 0, "off_end": 5, "wtype": "word", "next_word": 1, "sentence_index": 0, "sentence_index_neg": 3}, {"wf": "умирал", "off_start": 6, "off_end": 12, "wtype": "word", "next_word": 2, "sentence_index": 1, "sentence_index_neg": 2}, {"wf": "очень.", "off_start": 13, "off_end": 19, "wtype": "word", "next_word": 3, "sentence_index": 2, "sentence_index_neg": 1}], "lang": 1, "para_alignment": [{"off_start": 0, "off_end": 19, "para_id": 17}]}, {"text": "Мало осталось.", "words": [{"wf": "Мало", "off_start": 0, "off_end": 4, "wtype": "word", "next_word": 1, "sentence_index": 0, "sentence_index_neg": 2}, {"wf": "осталось.", "off_start": 5, "off_end": 14, "wtype": "word", "next_word": 2, "sentence_index": 1, "sentence_index_neg": 1}], "lang": 1, "para_alignment": [{"off_start": 0, "off_end": 14, "para_id": 18}]}]}