{"meta": {"filename": "171_200411_2_eve_annotated", "author": "NIGrigor", "year": "2004", "recplace": "Bystraja district", "title": "Женские", "genre": "newspaper"}, "sentences": [{"text": "Аси гургэн", "words": [{"wf": "Аси", "off_start": 0, "off_end": 3, "wtype": "word", "ana": [{"parts": "asi", "gloss": "женщина", "gloss_index": "женщина{asi}-"}], "next_word": 1, "sentence_index": 0, "sentence_index_neg": 2}, {"wf": "гургэн", "off_start": 4, "off_end": 10, "wtype": "word", "ana": [{"parts": "gurge-n", "gloss": "работа-poss.3sg", "gloss_index": "работа{gurge}-poss.3sg{n}-"}], "next_word": 2, "sentence_index": 1, "sentence_index_neg": 1}], "lang": 0, "para_alignment": [{"off_start": 0, "off_end": 10, "para_id": 0}]}, {"text": "Аси гургэн - игыдек, кочаидяк, дуктыдяк, аӈаныдяк.", "words": [{"wf": "Аси", "off_start": 0, "off_end": 3, "wtype": "word", "ana": [{"parts": "asi", "gloss": "женщина", "gloss_index": "женщина{asi}-"}], "next_word": 1, "sentence_index": 0, "sentence_index_neg": 6}, {"wf": "гургэн", "off_start": 4, "off_end": 10, "wtype": "word", "ana": [{"parts": "gurge-n", "gloss": "работа-poss.3sg", "gloss_index": "работа{gurge}-poss.3sg{n}-"}], "next_word": 2, "sentence_index": 1, "sentence_index_neg": 5}, {"wf": "игыдек,", "off_start": 13, "off_end": 20, "wtype": "word", "ana": [{"parts": "igəd'ek", "gloss": "IDK", "gloss_index": "IDK{igəd'ek}-"}], "next_word": 3, "sentence_index": 2, "sentence_index_neg": 4}, {"wf": "кочаидяк,", "off_start": 21, "off_end": 30, "wtype": "word", "ana": [{"parts": "kočaid'ak", "gloss": "IDK", "gloss_index": "IDK{kočaid'ak}-"}], "next_word": 4, "sentence_index": 3, "sentence_index_neg": 3}, {"wf": "дуктыдяк,", "off_start": 31, "off_end": 40, "wtype": "word", "ana": [{"parts": "duktəd'ak", "gloss": "IDK", "gloss_index": "IDK{duktəd'ak}-"}], "next_word": 5, "sentence_index": 4, "sentence_index_neg": 2}, {"wf": "аӈаныдяк.", "off_start": 41, "off_end": 50, "wtype": "word", "ana": [{"parts": "aŋanəd'ak", "gloss": "IDK", "gloss_index": "IDK{aŋanəd'ak}-"}], "next_word": 6, "sentence_index": 5, "sentence_index_neg": 1}], "lang": 0, "para_alignment": [{"off_start": 0, "off_end": 50, "para_id": 1}]}, {"text": "Орым игыдилми, дюллэтаӈняван атыллоттэ дил ойдэнун тобарыч.", "words": [{"wf": "Орым", "off_start": 0, "off_end": 4, "wtype": "word", "ana": [{"parts": "orə-m", "gloss": "олень-acc", "gloss_index": "олень{orə}-acc{m}-"}], "next_word": 1, "sentence_index": 0, "sentence_index_neg": 7}, {"wf": "игыдилми,", "off_start": 5, "off_end": 14, "wtype": "word", "ana": [{"parts": "igəd'ilmi", "gloss": "IDK", "gloss_index": "IDK{igəd'ilmi}-"}], "next_word": 2, "sentence_index": 1, "sentence_index_neg": 6}, {"wf": "дюллэтаӈняван", "off_start": 15, "off_end": 28, "wtype": "word", "ana": [{"parts": "d'ulletaŋn'awan", "gloss": "IDK", "gloss_index": "IDK{d'ulletaŋn'awan}-"}], "next_word": 3, "sentence_index": 2, "sentence_index_neg": 5}, {"wf": "атыллоттэ", "off_start": 29, "off_end": 38, "wtype": "word", "ana": [{"parts": "atəllotte", "gloss": "IDK", "gloss_index": "IDK{atəllotte}-"}], "next_word": 4, "sentence_index": 3, "sentence_index_neg": 4}, {"wf": "дил", "off_start": 39, "off_end": 42, "wtype": "word", "ana": [{"parts": "d'il", "gloss": "IDK", "gloss_index": "IDK{d'il}-"}], "next_word": 5, "sentence_index": 4, "sentence_index_neg": 3}, {"wf": "ойдэнун", "off_start": 43, "off_end": 50, "wtype": "word", "ana": [{"parts": "ojdenun", "gloss": "IDK", "gloss_index": "IDK{ojdenun}-"}], "next_word": 6, "sentence_index": 5, "sentence_index_neg": 2}, {"wf": "тобарыч.", "off_start": 51, "off_end": 59, "wtype": "word", "ana": [{"parts": "tobar-əč", "gloss": "топор-ins", "gloss_index": "топор{tobar}-ins{əč}-"}], "next_word": 7, "sentence_index": 6, "sentence_index_neg": 1}], "lang": 0, "para_alignment": [{"off_start": 0, "off_end": 59, "para_id": 2}]}, {"text": "Часки эсэкич, эмэндукун минэсноттэ иргыткин урын ойдэлин.", "words": [{"wf": "Часки", "off_start": 0, "off_end": 5, "wtype": "word", "ana": [{"parts": "časki", "gloss": "дальше", "gloss_index": "дальше{časki}-"}], "next_word": 1, "sentence_index": 0, "sentence_index_neg": 7}, {"wf": "эсэкич,", "off_start": 6, "off_end": 13, "wtype": "word", "ana": [{"parts": "esekič", "gloss": "IDK", "gloss_index": "IDK{esekič}-"}], "next_word": 2, "sentence_index": 1, "sentence_index_neg": 6}, {"wf": "эмэндукун", "off_start": 14, "off_end": 23, "wtype": "word", "ana": [{"parts": "emendukun", "gloss": "IDK", "gloss_index": "IDK{emendukun}-"}], "next_word": 3, "sentence_index": 2, "sentence_index_neg": 5}, {"wf": "минэсноттэ", "off_start": 24, "off_end": 34, "wtype": "word", "ana": [{"parts": "minesnotte", "gloss": "IDK", "gloss_index": "IDK{minesnotte}-"}], "next_word": 4, "sentence_index": 3, "sentence_index_neg": 4}, {"wf": "иргыткин", "off_start": 35, "off_end": 43, "wtype": "word", "ana": [{"parts": "irgətkin", "gloss": "IDK", "gloss_index": "IDK{irgətkin}-"}], "next_word": 5, "sentence_index": 4, "sentence_index_neg": 3}, {"wf": "урын", "off_start": 44, "off_end": 48, "wtype": "word", "ana": [{"parts": "urən", "gloss": "IDK", "gloss_index": "IDK{urən}-"}], "next_word": 6, "sentence_index": 5, "sentence_index_neg": 2}, {"wf": "ойдэлин.", "off_start": 49, "off_end": 57, "wtype": "word", "ana": [{"parts": "ojdelin", "gloss": "IDK", "gloss_index": "IDK{ojdelin}-"}], "next_word": 7, "sentence_index": 6, "sentence_index_neg": 1}], "lang": 0, "para_alignment": [{"off_start": 0, "off_end": 57, "para_id": 3}]}, {"text": "Ису атыллоттэ ӈалдюр урдук, нян атыллотэ дилу, будылылбэ, нуватты мявым, бостылбы, акым, звтэ, Ур додукун илтэв, уӈэлудэ.", "words": [{"wf": "Ису", "off_start": 0, "off_end": 3, "wtype": "word", "ana": [{"parts": "isu", "gloss": "IDK", "gloss_index": "IDK{isu}-"}], "next_word": 1, "sentence_index": 0, "sentence_index_neg": 17}, {"wf": "атыллоттэ", "off_start": 4, "off_end": 13, "wtype": "word", "ana": [{"parts": "atəllotte", "gloss": "IDK", "gloss_index": "IDK{atəllotte}-"}], "next_word": 2, "sentence_index": 1, "sentence_index_neg": 16}, {"wf": "ӈалдюр", "off_start": 14, "off_end": 20, "wtype": "word", "ana": [{"parts": "ŋald'ur", "gloss": "IDK", "gloss_index": "IDK{ŋald'ur}-"}], "next_word": 3, "sentence_index": 2, "sentence_index_neg": 15}, {"wf": "урдук,", "off_start": 21, "off_end": 27, "wtype": "word", "ana": [{"parts": "urduk", "gloss": "IDK", "gloss_index": "IDK{urduk}-"}], "next_word": 4, "sentence_index": 3, "sentence_index_neg": 14}, {"wf": "нян", "off_start": 28, "off_end": 31, "wtype": "word", "ana": [{"parts": "n'an", "gloss": "и", "gloss_index": "и{n'an}-"}], "next_word": 5, "sentence_index": 4, "sentence_index_neg": 13}, {"wf": "атыллотэ", "off_start": 32, "off_end": 40, "wtype": "word", "ana": [{"parts": "atəllote", "gloss": "IDK", "gloss_index": "IDK{atəllote}-"}], "next_word": 6, "sentence_index": 5, "sentence_index_neg": 12}, {"wf": "дилу,", "off_start": 41, "off_end": 46, "wtype": "word", "ana": [{"parts": "d'ilu", "gloss": "IDK", "gloss_index": "IDK{d'ilu}-"}], "next_word": 7, "sentence_index": 6, "sentence_index_neg": 11}, {"wf": "будылылбэ,", "off_start": 47, "off_end": 57, "wtype": "word", "ana": [{"parts": "budələlbe", "gloss": "IDK", "gloss_index": "IDK{budələlbe}-"}], "next_word": 8, "sentence_index": 7, "sentence_index_neg": 10}, {"wf": "нуватты", "off_start": 58, "off_end": 65, "wtype": "word", "ana": [{"parts": "nuwattə", "gloss": "IDK", "gloss_index": "IDK{nuwattə}-"}], "next_word": 9, "sentence_index": 8, "sentence_index_neg": 9}, {"wf": "мявым,", "off_start": 66, "off_end": 72, "wtype": "word", "ana": [{"parts": "m'awəm", "gloss": "IDK", "gloss_index": "IDK{m'awəm}-"}], "next_word": 10, "sentence_index": 9, "sentence_index_neg": 8}, {"wf": "бостылбы,", "off_start": 73, "off_end": 82, "wtype": "word", "ana": [{"parts": "bostəlbə", "gloss": "IDK", "gloss_index": "IDK{bostəlbə}-"}], "next_word": 11, "sentence_index": 10, "sentence_index_neg": 7}, {"wf": "акым,", "off_start": 83, "off_end": 88, "wtype": "word", "ana": [{"parts": "akəm", "gloss": "IDK", "gloss_index": "IDK{akəm}-"}], "next_word": 12, "sentence_index": 11, "sentence_index_neg": 6}, {"wf": "звтэ,", "off_start": 89, "off_end": 94, "wtype": "word", "ana": [{"parts": "ewte", "gloss": "звтэ", "gloss_index": "звтэ{ewte}-"}], "next_word": 13, "sentence_index": 12, "sentence_index_neg": 5}, {"wf": "Ур", "off_start": 95, "off_end": 97, "wtype": "word", "ana": [{"parts": "ur", "gloss": "IDK", "gloss_index": "IDK{ur}-"}], "next_word": 14, "sentence_index": 13, "sentence_index_neg": 4}, {"wf": "додукун", "off_start": 98, "off_end": 105, "wtype": "word", "ana": [{"parts": "dodukun", "gloss": "IDK", "gloss_index": "IDK{dodukun}-"}], "next_word": 15, "sentence_index": 14, "sentence_index_neg": 3}, {"wf": "илтэв,", "off_start": 106, "off_end": 112, "wtype": "word", "ana": [{"parts": "iltew", "gloss": "IDK", "gloss_index": "IDK{iltew}-"}], "next_word": 16, "sentence_index": 15, "sentence_index_neg": 2}, {"wf": "уӈэлудэ.", "off_start": 113, "off_end": 121, "wtype": "word", "ana": [{"parts": "uŋelude", "gloss": "IDK", "gloss_index": "IDK{uŋelude}-"}], "next_word": 17, "sentence_index": 16, "sentence_index_neg": 1}], "lang": 0, "para_alignment": [{"off_start": 0, "off_end": 121, "para_id": 4}]}, {"text": "Кэнтэрэв алладин минэкэтчоттэ: будылылбэн, мирылбэн, таӈэну, оч.", "words": [{"wf": "Кэнтэрэв", "off_start": 0, "off_end": 8, "wtype": "word", "ana": [{"parts": "kenterew", "gloss": "IDK", "gloss_index": "IDK{kenterew}-"}], "next_word": 1, "sentence_index": 0, "sentence_index_neg": 7}, {"wf": "алладин", "off_start": 9, "off_end": 16, "wtype": "word", "ana": [{"parts": "allad'in", "gloss": "IDK", "gloss_index": "IDK{allad'in}-"}], "next_word": 2, "sentence_index": 1, "sentence_index_neg": 6}, {"wf": "минэкэтчоттэ:", "off_start": 17, "off_end": 30, "wtype": "word", "ana": [{"parts": "mineketčotte", "gloss": "IDK", "gloss_index": "IDK{mineketčotte}-"}], "next_word": 3, "sentence_index": 2, "sentence_index_neg": 5}, {"wf": "будылылбэн,", "off_start": 31, "off_end": 42, "wtype": "word", "ana": [{"parts": "budələlben", "gloss": "IDK", "gloss_index": "IDK{budələlben}-"}], "next_word": 4, "sentence_index": 3, "sentence_index_neg": 4}, {"wf": "мирылбэн,", "off_start": 43, "off_end": 52, "wtype": "word", "ana": [{"parts": "mirəlben", "gloss": "IDK", "gloss_index": "IDK{mirəlben}-"}], "next_word": 5, "sentence_index": 4, "sentence_index_neg": 3}, {"wf": "таӈэну,", "off_start": 53, "off_end": 60, "wtype": "word", "ana": [{"parts": "taŋenu", "gloss": "IDK", "gloss_index": "IDK{taŋenu}-"}], "next_word": 6, "sentence_index": 5, "sentence_index_neg": 2}, {"wf": "оч.", "off_start": 61, "off_end": 64, "wtype": "word", "ana": [{"parts": "oč", "gloss": "IDK", "gloss_index": "IDK{oč}-"}], "next_word": 7, "sentence_index": 6, "sentence_index_neg": 1}], "lang": 0, "para_alignment": [{"off_start": 0, "off_end": 64, "para_id": 5}]}, {"text": "Ислыбы аточлмидюр таракымтэ олгитчоттэ, аич тэссидюр имсыдук, иртэван.", "words": [{"wf": "Ислыбы", "off_start": 0, "off_end": 6, "wtype": "word", "ana": [{"parts": "isləbə", "gloss": "IDK", "gloss_index": "IDK{isləbə}-"}], "next_word": 1, "sentence_index": 0, "sentence_index_neg": 8}, {"wf": "аточлмидюр", "off_start": 7, "off_end": 17, "wtype": "word", "ana": [{"parts": "atočlmid'ur", "gloss": "IDK", "gloss_index": "IDK{atočlmid'ur}-"}], "next_word": 2, "sentence_index": 1, "sentence_index_neg": 7}, {"wf": "таракымтэ", "off_start": 18, "off_end": 27, "wtype": "word", "ana": [{"parts": "tarakəmte", "gloss": "IDK", "gloss_index": "IDK{tarakəmte}-"}], "next_word": 3, "sentence_index": 2, "sentence_index_neg": 6}, {"wf": "олгитчоттэ,", "off_start": 28, "off_end": 39, "wtype": "word", "ana": [{"parts": "olgitčotte", "gloss": "IDK", "gloss_index": "IDK{olgitčotte}-"}], "next_word": 4, "sentence_index": 3, "sentence_index_neg": 5}, {"wf": "аич", "off_start": 40, "off_end": 43, "wtype": "word", "ana": [{"parts": "ai-č", "gloss": "хороший-ins", "gloss_index": "хороший{ai}-ins{č}-"}], "next_word": 5, "sentence_index": 4, "sentence_index_neg": 4}, {"wf": "тэссидюр", "off_start": 44, "off_end": 52, "wtype": "word", "ana": [{"parts": "tessid'ur", "gloss": "IDK", "gloss_index": "IDK{tessid'ur}-"}], "next_word": 6, "sentence_index": 5, "sentence_index_neg": 3}, {"wf": "имсыдук,", "off_start": 53, "off_end": 61, "wtype": "word", "ana": [{"parts": "imsəduk", "gloss": "IDK", "gloss_index": "IDK{imsəduk}-"}], "next_word": 7, "sentence_index": 6, "sentence_index_neg": 2}, {"wf": "иртэван.", "off_start": 62, "off_end": 70, "wtype": "word", "ana": [{"parts": "irtewan", "gloss": "IDK", "gloss_index": "IDK{irtewan}-"}], "next_word": 8, "sentence_index": 7, "sentence_index_neg": 1}], "lang": 0, "para_alignment": [{"off_start": 0, "off_end": 70, "para_id": 6}]}, {"text": "Ис улилин делыч тэнивэтты аич таӈчиникэн, тарыкым аич таӈчими, ис эгден один.", "words": [{"wf": "Ис", "off_start": 0, "off_end": 2, "wtype": "word", "ana": [{"parts": "is", "gloss": "IDK", "gloss_index": "IDK{is}-"}], "next_word": 1, "sentence_index": 0, "sentence_index_neg": 12}, {"wf": "улилин", "off_start": 3, "off_end": 9, "wtype": "word", "ana": [{"parts": "uli-li-n", "gloss": "край-prol-3sg", "gloss_index": "край{uli}-prol{li}-3sg{n}-"}], "next_word": 2, "sentence_index": 1, "sentence_index_neg": 11}, {"wf": "делыч", "off_start": 10, "off_end": 15, "wtype": "word", "ana": [{"parts": "d'eləč", "gloss": "IDK", "gloss_index": "IDK{d'eləč}-"}], "next_word": 3, "sentence_index": 2, "sentence_index_neg": 10}, {"wf": "тэнивэтты", "off_start": 16, "off_end": 25, "wtype": "word", "ana": [{"parts": "teniwettə", "gloss": "IDK", "gloss_index": "IDK{teniwettə}-"}], "next_word": 4, "sentence_index": 3, "sentence_index_neg": 9}, {"wf": "аич", "off_start": 26, "off_end": 29, "wtype": "word", "ana": [{"parts": "ai-č", "gloss": "хороший-ins", "gloss_index": "хороший{ai}-ins{č}-"}], "next_word": 5, "sentence_index": 4, "sentence_index_neg": 8}, {"wf": "таӈчиникэн,", "off_start": 30, "off_end": 41, "wtype": "word", "ana": [{"parts": "taŋčiniken", "gloss": "IDK", "gloss_index": "IDK{taŋčiniken}-"}], "next_word": 6, "sentence_index": 5, "sentence_index_neg": 7}, {"wf": "тарыкым", "off_start": 42, "off_end": 49, "wtype": "word", "ana": [{"parts": "tarəkə-m", "gloss": "dem.dist-acc", "gloss_index": "dem.dist{tarəkə}-acc{m}-"}], "next_word": 7, "sentence_index": 6, "sentence_index_neg": 6}, {"wf": "аич", "off_start": 50, "off_end": 53, "wtype": "word", "ana": [{"parts": "ai-č", "gloss": "хороший-ins", "gloss_index": "хороший{ai}-ins{č}-"}], "next_word": 8, "sentence_index": 7, "sentence_index_neg": 5}, {"wf": "таӈчими,", "off_start": 54, "off_end": 62, "wtype": "word", "ana": [{"parts": "taŋčimi", "gloss": "IDK", "gloss_index": "IDK{taŋčimi}-"}], "next_word": 9, "sentence_index": 8, "sentence_index_neg": 4}, {"wf": "ис", "off_start": 63, "off_end": 65, "wtype": "word", "ana": [{"parts": "is", "gloss": "IDK", "gloss_index": "IDK{is}-"}], "next_word": 10, "sentence_index": 9, "sentence_index_neg": 3}, {"wf": "эгден", "off_start": 66, "off_end": 71, "wtype": "word", "ana": [{"parts": "egd'en", "gloss": "большой", "gloss_index": "большой{egd'en}-"}], "next_word": 11, "sentence_index": 10, "sentence_index_neg": 2}, {"wf": "один.", "off_start": 72, "off_end": 77, "wtype": "word", "ana": [{"parts": "o-d'i-n", "gloss": "стать-fut-3sg", "gloss_index": "стать{o}-fut{d'i}-3sg{n}-"}], "next_word": 12, "sentence_index": 11, "sentence_index_neg": 1}], "lang": 0, "para_alignment": [{"off_start": 0, "off_end": 77, "para_id": 7}]}, {"text": "Айи бидин мокаканыл туручивми ису туурми типкэникэр.", "words": [{"wf": "Айи", "off_start": 0, "off_end": 3, "wtype": "word", "ana": [{"parts": "aji", "gloss": "IDK", "gloss_index": "IDK{aji}-"}], "next_word": 1, "sentence_index": 0, "sentence_index_neg": 7}, {"wf": "бидин", "off_start": 4, "off_end": 9, "wtype": "word", "ana": [{"parts": "bi-d'i-n", "gloss": "быть-fut-3sg", "gloss_index": "быть{bi}-fut{d'i}-3sg{n}-"}], "next_word": 2, "sentence_index": 1, "sentence_index_neg": 6}, {"wf": "мокаканыл", "off_start": 10, "off_end": 19, "wtype": "word", "ana": [{"parts": "mokakanəl", "gloss": "IDK", "gloss_index": "IDK{mokakanəl}-"}], "next_word": 3, "sentence_index": 2, "sentence_index_neg": 5}, {"wf": "туручивми", "off_start": 20, "off_end": 29, "wtype": "word", "ana": [{"parts": "turučiwmi", "gloss": "IDK", "gloss_index": "IDK{turučiwmi}-"}], "next_word": 4, "sentence_index": 3, "sentence_index_neg": 4}, {"wf": "ису", "off_start": 30, "off_end": 33, "wtype": "word", "ana": [{"parts": "isu", "gloss": "IDK", "gloss_index": "IDK{isu}-"}], "next_word": 5, "sentence_index": 4, "sentence_index_neg": 3}, {"wf": "туурми", "off_start": 34, "off_end": 40, "wtype": "word", "ana": [{"parts": "tuurmi", "gloss": "IDK", "gloss_index": "IDK{tuurmi}-"}], "next_word": 6, "sentence_index": 5, "sentence_index_neg": 2}, {"wf": "типкэникэр.", "off_start": 41, "off_end": 52, "wtype": "word", "ana": [{"parts": "tipkeniker", "gloss": "IDK", "gloss_index": "IDK{tipkeniker}-"}], "next_word": 7, "sentence_index": 6, "sentence_index_neg": 1}], "lang": 0, "para_alignment": [{"off_start": 0, "off_end": 52, "para_id": 8}]}, {"text": "Олгырыкын ис нян кочаидиллоттэ.", "words": [{"wf": "Олгырыкын", "off_start": 0, "off_end": 9, "wtype": "word", "ana": [{"parts": "olgərəkən", "gloss": "IDK", "gloss_index": "IDK{olgərəkən}-"}], "next_word": 1, "sentence_index": 0, "sentence_index_neg": 4}, {"wf": "ис", "off_start": 10, "off_end": 12, "wtype": "word", "ana": [{"parts": "is", "gloss": "IDK", "gloss_index": "IDK{is}-"}], "next_word": 2, "sentence_index": 1, "sentence_index_neg": 3}, {"wf": "нян", "off_start": 13, "off_end": 16, "wtype": "word", "ana": [{"parts": "n'an", "gloss": "и", "gloss_index": "и{n'an}-"}], "next_word": 3, "sentence_index": 2, "sentence_index_neg": 2}, {"wf": "кочаидиллоттэ.", "off_start": 17, "off_end": 31, "wtype": "word", "ana": [{"parts": "kočaid'illotte", "gloss": "IDK", "gloss_index": "IDK{kočaid'illotte}-"}], "next_word": 4, "sentence_index": 3, "sentence_index_neg": 1}], "lang": 0, "para_alignment": [{"off_start": 0, "off_end": 31, "para_id": 9}]}, {"text": "Кочай чивер бэилӈин умынылки—дёлдук.", "words": [{"wf": "Кочай", "off_start": 0, "off_end": 5, "wtype": "word", "ana": [{"parts": "kočaj", "gloss": "IDK", "gloss_index": "IDK{kočaj}-"}], "next_word": 1, "sentence_index": 0, "sentence_index_neg": 4}, {"wf": "чивер", "off_start": 6, "off_end": 11, "wtype": "word", "ana": [{"parts": "čiw'er", "gloss": "IDK", "gloss_index": "IDK{čiw'er}-"}], "next_word": 2, "sentence_index": 1, "sentence_index_neg": 3}, {"wf": "бэилӈин", "off_start": 12, "off_end": 19, "wtype": "word", "ana": [{"parts": "beilŋin", "gloss": "IDK", "gloss_index": "IDK{beilŋin}-"}], "next_word": 3, "sentence_index": 2, "sentence_index_neg": 2}, {"wf": "умынылки—дёлдук.", "off_start": 20, "off_end": 36, "wtype": "word", "ana": [{"parts": "umənəlki—d'olduk", "gloss": "IDK", "gloss_index": "IDK{umənəlki—d'olduk}-"}], "next_word": 4, "sentence_index": 3, "sentence_index_neg": 1}], "lang": 0, "para_alignment": [{"off_start": 0, "off_end": 36, "para_id": 10}]}, {"text": "Дёлу туллоттэ мола;", "words": [{"wf": "Дёлу", "off_start": 0, "off_end": 4, "wtype": "word", "ana": [{"parts": "d'olu", "gloss": "IDK", "gloss_index": "IDK{d'olu}-"}], "next_word": 1, "sentence_index": 0, "sentence_index_neg": 3}, {"wf": "туллоттэ", "off_start": 5, "off_end": 13, "wtype": "word", "ana": [{"parts": "tullotte", "gloss": "IDK", "gloss_index": "IDK{tullotte}-"}], "next_word": 2, "sentence_index": 1, "sentence_index_neg": 2}, {"wf": "мола;", "off_start": 14, "off_end": 19, "wtype": "word", "ana": [{"parts": "mo-la", "gloss": "дерево-loc", "gloss_index": "дерево{mo}-loc{la}-"}], "next_word": 3, "sentence_index": 2, "sentence_index_neg": 1}], "lang": 0, "para_alignment": [{"off_start": 0, "off_end": 19, "para_id": 11}]}, {"text": "Ӈалдюр гаваттэ кочаю, ису нэвэттэ доскали булдутили, будыл ойдэлин нэдидюр кочаидиллоттэ, ису улыснидюр.", "words": [{"wf": "Ӈалдюр", "off_start": 0, "off_end": 6, "wtype": "word", "ana": [{"parts": "ŋald'ur", "gloss": "IDK", "gloss_index": "IDK{ŋald'ur}-"}], "next_word": 1, "sentence_index": 0, "sentence_index_neg": 13}, {"wf": "гаваттэ", "off_start": 7, "off_end": 14, "wtype": "word", "ana": [{"parts": "gawatte", "gloss": "IDK", "gloss_index": "IDK{gawatte}-"}], "next_word": 2, "sentence_index": 1, "sentence_index_neg": 12}, {"wf": "кочаю,", "off_start": 15, "off_end": 21, "wtype": "word", "ana": [{"parts": "kočaju", "gloss": "IDK", "gloss_index": "IDK{kočaju}-"}], "next_word": 3, "sentence_index": 2, "sentence_index_neg": 11}, {"wf": "ису", "off_start": 22, "off_end": 25, "wtype": "word", "ana": [{"parts": "isu", "gloss": "IDK", "gloss_index": "IDK{isu}-"}], "next_word": 4, "sentence_index": 3, "sentence_index_neg": 10}, {"wf": "нэвэттэ", "off_start": 26, "off_end": 33, "wtype": "word", "ana": [{"parts": "newette", "gloss": "IDK", "gloss_index": "IDK{newette}-"}], "next_word": 5, "sentence_index": 4, "sentence_index_neg": 9}, {"wf": "доскали", "off_start": 34, "off_end": 41, "wtype": "word", "ana": [{"parts": "doskali", "gloss": "IDK", "gloss_index": "IDK{doskali}-"}], "next_word": 6, "sentence_index": 5, "sentence_index_neg": 8}, {"wf": "булдутили,", "off_start": 42, "off_end": 52, "wtype": "word", "ana": [{"parts": "buldutili", "gloss": "IDK", "gloss_index": "IDK{buldutili}-"}], "next_word": 7, "sentence_index": 6, "sentence_index_neg": 7}, {"wf": "будыл", "off_start": 53, "off_end": 58, "wtype": "word", "ana": [{"parts": "budəl", "gloss": "IDK", "gloss_index": "IDK{budəl}-"}], "next_word": 8, "sentence_index": 7, "sentence_index_neg": 6}, {"wf": "ойдэлин", "off_start": 59, "off_end": 66, "wtype": "word", "ana": [{"parts": "ojdelin", "gloss": "IDK", "gloss_index": "IDK{ojdelin}-"}], "next_word": 9, "sentence_index": 8, "sentence_index_neg": 5}, {"wf": "нэдидюр", "off_start": 67, "off_end": 74, "wtype": "word", "ana": [{"parts": "ned'id'ur", "gloss": "IDK", "gloss_index": "IDK{ned'id'ur}-"}], "next_word": 10, "sentence_index": 9, "sentence_index_neg": 4}, {"wf": "кочаидиллоттэ,", "off_start": 75, "off_end": 89, "wtype": "word", "ana": [{"parts": "kočaid'illotte", "gloss": "IDK", "gloss_index": "IDK{kočaid'illotte}-"}], "next_word": 11, "sentence_index": 10, "sentence_index_neg": 3}, {"wf": "ису", "off_start": 90, "off_end": 93, "wtype": "word", "ana": [{"parts": "isu", "gloss": "IDK", "gloss_index": "IDK{isu}-"}], "next_word": 12, "sentence_index": 11, "sentence_index_neg": 2}, {"wf": "улыснидюр.", "off_start": 94, "off_end": 104, "wtype": "word", "ana": [{"parts": "uləsnid'ur", "gloss": "IDK", "gloss_index": "IDK{uləsnid'ur}-"}], "next_word": 13, "sentence_index": 12, "sentence_index_neg": 1}], "lang": 0, "para_alignment": [{"off_start": 0, "off_end": 104, "para_id": 12}]}, {"text": "Адиракан кочайридюр, адатиӈыч эсивэтты, нянда кочайры.", "words": [{"wf": "Адиракан", "off_start": 0, "off_end": 8, "wtype": "word", "ana": [{"parts": "ad'irakan", "gloss": "IDK", "gloss_index": "IDK{ad'irakan}-"}], "next_word": 1, "sentence_index": 0, "sentence_index_neg": 6}, {"wf": "кочайридюр,", "off_start": 9, "off_end": 20, "wtype": "word", "ana": [{"parts": "kočajrid'ur", "gloss": "IDK", "gloss_index": "IDK{kočajrid'ur}-"}], "next_word": 2, "sentence_index": 1, "sentence_index_neg": 5}, {"wf": "адатиӈыч", "off_start": 21, "off_end": 29, "wtype": "word", "ana": [{"parts": "adatiŋəč", "gloss": "IDK", "gloss_index": "IDK{adatiŋəč}-"}], "next_word": 3, "sentence_index": 2, "sentence_index_neg": 4}, {"wf": "эсивэтты,", "off_start": 30, "off_end": 39, "wtype": "word", "ana": [{"parts": "esiwettə", "gloss": "IDK", "gloss_index": "IDK{esiwettə}-"}], "next_word": 4, "sentence_index": 3, "sentence_index_neg": 3}, {"wf": "нянда", "off_start": 40, "off_end": 45, "wtype": "word", "ana": [{"parts": "n'anda", "gloss": "IDK", "gloss_index": "IDK{n'anda}-"}], "next_word": 5, "sentence_index": 4, "sentence_index_neg": 2}, {"wf": "кочайры.", "off_start": 46, "off_end": 54, "wtype": "word", "ana": [{"parts": "kočajrə", "gloss": "IDK", "gloss_index": "IDK{kočajrə}-"}], "next_word": 6, "sentence_index": 5, "sentence_index_neg": 1}], "lang": 0, "para_alignment": [{"off_start": 0, "off_end": 54, "para_id": 13}]}, {"text": "Адатин, ису тэмбыргывкэвэттын.", "words": [{"wf": "Адатин,", "off_start": 0, "off_end": 7, "wtype": "word", "ana": [{"parts": "adatin", "gloss": "IDK", "gloss_index": "IDK{adatin}-"}], "next_word": 1, "sentence_index": 0, "sentence_index_neg": 3}, {"wf": "ису", "off_start": 8, "off_end": 11, "wtype": "word", "ana": [{"parts": "isu", "gloss": "IDK", "gloss_index": "IDK{isu}-"}], "next_word": 2, "sentence_index": 1, "sentence_index_neg": 2}, {"wf": "тэмбыргывкэвэттын.", "off_start": 12, "off_end": 30, "wtype": "word", "ana": [{"parts": "tembərgəwkewettən", "gloss": "IDK", "gloss_index": "IDK{tembərgəwkewettən}-"}], "next_word": 3, "sentence_index": 2, "sentence_index_neg": 1}], "lang": 0, "para_alignment": [{"off_start": 0, "off_end": 30, "para_id": 14}]}, {"text": "Эсивэтты ису дуктыч адиракантыда.", "words": [{"wf": "Эсивэтты", "off_start": 0, "off_end": 8, "wtype": "word", "ana": [{"parts": "esiwettə", "gloss": "IDK", "gloss_index": "IDK{esiwettə}-"}], "next_word": 1, "sentence_index": 0, "sentence_index_neg": 4}, {"wf": "ису", "off_start": 9, "off_end": 12, "wtype": "word", "ana": [{"parts": "isu", "gloss": "IDK", "gloss_index": "IDK{isu}-"}], "next_word": 2, "sentence_index": 1, "sentence_index_neg": 3}, {"wf": "дуктыч", "off_start": 13, "off_end": 19, "wtype": "word", "ana": [{"parts": "duktəč", "gloss": "IDK", "gloss_index": "IDK{duktəč}-"}], "next_word": 3, "sentence_index": 2, "sentence_index_neg": 2}, {"wf": "адиракантыда.", "off_start": 20, "off_end": 33, "wtype": "word", "ana": [{"parts": "ad'irakantəda", "gloss": "IDK", "gloss_index": "IDK{ad'irakantəda}-"}], "next_word": 4, "sentence_index": 3, "sentence_index_neg": 1}], "lang": 0, "para_alignment": [{"off_start": 0, "off_end": 33, "para_id": 15}]}, {"text": "Таракам ис этэндэ улыбнар.", "words": [{"wf": "Таракам", "off_start": 0, "off_end": 7, "wtype": "word", "ana": [{"parts": "taraka-m", "gloss": "dem.dist-acc", "gloss_index": "dem.dist{taraka}-acc{m}-"}], "next_word": 1, "sentence_index": 0, "sentence_index_neg": 4}, {"wf": "ис", "off_start": 8, "off_end": 10, "wtype": "word", "ana": [{"parts": "is", "gloss": "IDK", "gloss_index": "IDK{is}-"}], "next_word": 2, "sentence_index": 1, "sentence_index_neg": 3}, {"wf": "этэндэ", "off_start": 11, "off_end": 17, "wtype": "word", "ana": [{"parts": "e-te-n=de", "gloss": "neg.aux-nfut-3sg=add", "gloss_index": "neg.aux{e}-nfut{te}-3sg=add{n=de}-"}], "next_word": 3, "sentence_index": 2, "sentence_index_neg": 2}, {"wf": "улыбнар.", "off_start": 18, "off_end": 26, "wtype": "word", "ana": [{"parts": "uləbnar", "gloss": "IDK", "gloss_index": "IDK{uləbnar}-"}], "next_word": 4, "sentence_index": 3, "sentence_index_neg": 1}], "lang": 0, "para_alignment": [{"off_start": 0, "off_end": 26, "para_id": 16}]}, {"text": "Адатин, бивэттын акындук, колалидук, орында помйтын.", "words": [{"wf": "Адатин,", "off_start": 0, "off_end": 7, "wtype": "word", "ana": [{"parts": "adatin", "gloss": "IDK", "gloss_index": "IDK{adatin}-"}], "next_word": 1, "sentence_index": 0, "sentence_index_neg": 6}, {"wf": "бивэттын", "off_start": 8, "off_end": 16, "wtype": "word", "ana": [{"parts": "bi-wet-tə-n", "gloss": "быть-freq-pst-3sg", "gloss_index": "быть{bi}-freq{wet}-pst{tə}-3sg{n}-"}], "next_word": 2, "sentence_index": 1, "sentence_index_neg": 5}, {"wf": "акындук,", "off_start": 17, "off_end": 25, "wtype": "word", "ana": [{"parts": "akənduk", "gloss": "IDK", "gloss_index": "IDK{akənduk}-"}], "next_word": 3, "sentence_index": 2, "sentence_index_neg": 4}, {"wf": "колалидук,", "off_start": 26, "off_end": 36, "wtype": "word", "ana": [{"parts": "kolaliduk", "gloss": "IDK", "gloss_index": "IDK{kolaliduk}-"}], "next_word": 4, "sentence_index": 3, "sentence_index_neg": 3}, {"wf": "орында", "off_start": 37, "off_end": 43, "wtype": "word", "ana": [{"parts": "orənda", "gloss": "IDK", "gloss_index": "IDK{orənda}-"}], "next_word": 5, "sentence_index": 4, "sentence_index_neg": 2}, {"wf": "помйтын.", "off_start": 44, "off_end": 52, "wtype": "word", "ana": [{"parts": "pomjtən", "gloss": "IDK", "gloss_index": "IDK{pomjtən}-"}], "next_word": 6, "sentence_index": 5, "sentence_index_neg": 1}], "lang": 0, "para_alignment": [{"off_start": 0, "off_end": 52, "para_id": 17}]}, {"text": "Оярыкан кочайми ис тэмбыкын оваттын.", "words": [{"wf": "Оярыкан", "off_start": 0, "off_end": 7, "wtype": "word", "ana": [{"parts": "ojarəkan", "gloss": "IDK", "gloss_index": "IDK{ojarəkan}-"}], "next_word": 1, "sentence_index": 0, "sentence_index_neg": 5}, {"wf": "кочайми", "off_start": 8, "off_end": 15, "wtype": "word", "ana": [{"parts": "kočajmi", "gloss": "IDK", "gloss_index": "IDK{kočajmi}-"}], "next_word": 2, "sentence_index": 1, "sentence_index_neg": 4}, {"wf": "ис", "off_start": 16, "off_end": 18, "wtype": "word", "ana": [{"parts": "is", "gloss": "IDK", "gloss_index": "IDK{is}-"}], "next_word": 3, "sentence_index": 2, "sentence_index_neg": 3}, {"wf": "тэмбыкын", "off_start": 19, "off_end": 27, "wtype": "word", "ana": [{"parts": "tembəkən", "gloss": "IDK", "gloss_index": "IDK{tembəkən}-"}], "next_word": 4, "sentence_index": 3, "sentence_index_neg": 2}, {"wf": "оваттын.", "off_start": 28, "off_end": 36, "wtype": "word", "ana": [{"parts": "owattən", "gloss": "IDK", "gloss_index": "IDK{owattən}-"}], "next_word": 5, "sentence_index": 4, "sentence_index_neg": 1}], "lang": 0, "para_alignment": [{"off_start": 0, "off_end": 36, "para_id": 18}]}, {"text": "Ис нюритон аич улиттидюр, нямдулэ нэкчивэтты дюр иныӈу, нилгитми тачин истук нюриттон аич атылыбдин.", "words": [{"wf": "Ис", "off_start": 0, "off_end": 2, "wtype": "word", "ana": [{"parts": "is", "gloss": "IDK", "gloss_index": "IDK{is}-"}], "next_word": 1, "sentence_index": 0, "sentence_index_neg": 14}, {"wf": "нюритон", "off_start": 3, "off_end": 10, "wtype": "word", "ana": [{"parts": "n'uriton", "gloss": "IDK", "gloss_index": "IDK{n'uriton}-"}], "next_word": 2, "sentence_index": 1, "sentence_index_neg": 13}, {"wf": "аич", "off_start": 11, "off_end": 14, "wtype": "word", "ana": [{"parts": "ai-č", "gloss": "хороший-ins", "gloss_index": "хороший{ai}-ins{č}-"}], "next_word": 3, "sentence_index": 2, "sentence_index_neg": 12}, {"wf": "улиттидюр,", "off_start": 15, "off_end": 25, "wtype": "word", "ana": [{"parts": "ulittid'ur", "gloss": "IDK", "gloss_index": "IDK{ulittid'ur}-"}], "next_word": 4, "sentence_index": 3, "sentence_index_neg": 11}, {"wf": "нямдулэ", "off_start": 26, "off_end": 33, "wtype": "word", "ana": [{"parts": "n'amdule", "gloss": "IDK", "gloss_index": "IDK{n'amdule}-"}], "next_word": 5, "sentence_index": 4, "sentence_index_neg": 10}, {"wf": "нэкчивэтты", "off_start": 34, "off_end": 44, "wtype": "word", "ana": [{"parts": "nekčiwettə", "gloss": "IDK", "gloss_index": "IDK{nekčiwettə}-"}], "next_word": 6, "sentence_index": 5, "sentence_index_neg": 9}, {"wf": "дюр", "off_start": 45, "off_end": 48, "wtype": "word", "ana": [{"parts": "d'ur", "gloss": "два", "gloss_index": "два{d'ur}-"}], "next_word": 7, "sentence_index": 6, "sentence_index_neg": 8}, {"wf": "иныӈу,", "off_start": 49, "off_end": 55, "wtype": "word", "ana": [{"parts": "inəŋ-u", "gloss": "день-acc", "gloss_index": "день{inəŋ}-acc{u}-"}], "next_word": 8, "sentence_index": 7, "sentence_index_neg": 7}, {"wf": "нилгитми", "off_start": 56, "off_end": 64, "wtype": "word", "ana": [{"parts": "nilgitmi", "gloss": "IDK", "gloss_index": "IDK{nilgitmi}-"}], "next_word": 9, "sentence_index": 8, "sentence_index_neg": 6}, {"wf": "тачин", "off_start": 65, "off_end": 70, "wtype": "word", "ana": [{"parts": "tačin", "gloss": "так", "gloss_index": "так{tačin}-"}], "next_word": 10, "sentence_index": 9, "sentence_index_neg": 5}, {"wf": "истук", "off_start": 71, "off_end": 76, "wtype": "word", "ana": [{"parts": "istuk", "gloss": "IDK", "gloss_index": "IDK{istuk}-"}], "next_word": 11, "sentence_index": 10, "sentence_index_neg": 4}, {"wf": "нюриттон", "off_start": 77, "off_end": 85, "wtype": "word", "ana": [{"parts": "n'uritton", "gloss": "IDK", "gloss_index": "IDK{n'uritton}-"}], "next_word": 12, "sentence_index": 11, "sentence_index_neg": 3}, {"wf": "аич", "off_start": 86, "off_end": 89, "wtype": "word", "ana": [{"parts": "ai-č", "gloss": "хороший-ins", "gloss_index": "хороший{ai}-ins{č}-"}], "next_word": 13, "sentence_index": 12, "sentence_index_neg": 2}, {"wf": "атылыбдин.", "off_start": 90, "off_end": 100, "wtype": "word", "ana": [{"parts": "atələbd'in", "gloss": "IDK", "gloss_index": "IDK{atələbd'in}-"}], "next_word": 14, "sentence_index": 13, "sentence_index_neg": 1}], "lang": 0, "para_alignment": [{"off_start": 0, "off_end": 100, "para_id": 19}]}, {"text": "Нилгитча истук унтум одир, гекив чаривда, ичигив, гекив-явкы аявыс.", "words": [{"wf": "Нилгитча", "off_start": 0, "off_end": 8, "wtype": "word", "ana": [{"parts": "nilgitča", "gloss": "IDK", "gloss_index": "IDK{nilgitča}-"}], "next_word": 1, "sentence_index": 0, "sentence_index_neg": 9}, {"wf": "истук", "off_start": 9, "off_end": 14, "wtype": "word", "ana": [{"parts": "istuk", "gloss": "IDK", "gloss_index": "IDK{istuk}-"}], "next_word": 2, "sentence_index": 1, "sentence_index_neg": 8}, {"wf": "унтум", "off_start": 15, "off_end": 20, "wtype": "word", "ana": [{"parts": "untum", "gloss": "IDK", "gloss_index": "IDK{untum}-"}], "next_word": 3, "sentence_index": 2, "sentence_index_neg": 7}, {"wf": "одир,", "off_start": 21, "off_end": 26, "wtype": "word", "ana": [{"parts": "od'ir", "gloss": "IDK", "gloss_index": "IDK{od'ir}-"}], "next_word": 4, "sentence_index": 3, "sentence_index_neg": 6}, {"wf": "гекив", "off_start": 27, "off_end": 32, "wtype": "word", "ana": [{"parts": "g'eki-w", "gloss": "разный-acc", "gloss_index": "разный{g'eki}-acc{w}-"}], "next_word": 5, "sentence_index": 4, "sentence_index_neg": 5}, {"wf": "чаривда,", "off_start": 33, "off_end": 41, "wtype": "word", "ana": [{"parts": "čariwda", "gloss": "IDK", "gloss_index": "IDK{čariwda}-"}], "next_word": 6, "sentence_index": 5, "sentence_index_neg": 4}, {"wf": "ичигив,", "off_start": 42, "off_end": 49, "wtype": "word", "ana": [{"parts": "ičigiw", "gloss": "IDK", "gloss_index": "IDK{ičigiw}-"}], "next_word": 7, "sentence_index": 6, "sentence_index_neg": 3}, {"wf": "гекив-явкы", "off_start": 50, "off_end": 60, "wtype": "word", "ana": [{"parts": "g'ekiw-jawkə", "gloss": "IDK", "gloss_index": "IDK{g'ekiw}-"}], "next_word": 8, "sentence_index": 7, "sentence_index_neg": 2}, {"wf": "аявыс.", "off_start": 61, "off_end": 67, "wtype": "word", "ana": [{"parts": "ajawəs", "gloss": "IDK", "gloss_index": "IDK{ajawəs}-"}], "next_word": 9, "sentence_index": 8, "sentence_index_neg": 1}], "lang": 0, "para_alignment": [{"off_start": 0, "off_end": 67, "para_id": 20}]}, {"text": "Кочайгав ису аниндула нокычидюкаватгыда, тачин оча ис этэн насамнэ, улыбнэр.", "words": [{"wf": "Кочайгав", "off_start": 0, "off_end": 8, "wtype": "word", "ana": [{"parts": "kočajgaw", "gloss": "IDK", "gloss_index": "IDK{kočajgaw}-"}], "next_word": 1, "sentence_index": 0, "sentence_index_neg": 10}, {"wf": "ису", "off_start": 9, "off_end": 12, "wtype": "word", "ana": [{"parts": "isu", "gloss": "IDK", "gloss_index": "IDK{isu}-"}], "next_word": 2, "sentence_index": 1, "sentence_index_neg": 9}, {"wf": "аниндула", "off_start": 13, "off_end": 21, "wtype": "word", "ana": [{"parts": "anindula", "gloss": "IDK", "gloss_index": "IDK{anindula}-"}], "next_word": 3, "sentence_index": 2, "sentence_index_neg": 8}, {"wf": "нокычидюкаватгыда,", "off_start": 22, "off_end": 40, "wtype": "word", "ana": [{"parts": "nokəčid'ukawatgəda", "gloss": "IDK", "gloss_index": "IDK{nokəčid'ukawatgəda}-"}], "next_word": 4, "sentence_index": 3, "sentence_index_neg": 7}, {"wf": "тачин", "off_start": 41, "off_end": 46, "wtype": "word", "ana": [{"parts": "tačin", "gloss": "так", "gloss_index": "так{tačin}-"}], "next_word": 5, "sentence_index": 4, "sentence_index_neg": 6}, {"wf": "оча", "off_start": 47, "off_end": 50, "wtype": "word", "ana": [{"parts": "o-ča", "gloss": "стать-ptc.pst", "gloss_index": "стать{o}-ptc.pst{ča}-"}], "next_word": 6, "sentence_index": 5, "sentence_index_neg": 5}, {"wf": "ис", "off_start": 51, "off_end": 53, "wtype": "word", "ana": [{"parts": "is", "gloss": "IDK", "gloss_index": "IDK{is}-"}], "next_word": 7, "sentence_index": 6, "sentence_index_neg": 4}, {"wf": "этэн", "off_start": 54, "off_end": 58, "wtype": "word", "ana": [{"parts": "e-t-te-n", "gloss": "neg.aux-prog-nfut-3sg", "gloss_index": "neg.aux{e}-prog{t}-nfut{te}-3sg{n}-"}], "next_word": 8, "sentence_index": 7, "sentence_index_neg": 3}, {"wf": "насамнэ,", "off_start": 59, "off_end": 67, "wtype": "word", "ana": [{"parts": "nasamne", "gloss": "IDK", "gloss_index": "IDK{nasamne}-"}], "next_word": 9, "sentence_index": 8, "sentence_index_neg": 2}, {"wf": "улыбнэр.", "off_start": 68, "off_end": 76, "wtype": "word", "ana": [{"parts": "uləbner", "gloss": "IDK", "gloss_index": "IDK{uləbner}-"}], "next_word": 10, "sentence_index": 9, "sentence_index_neg": 1}], "lang": 0, "para_alignment": [{"off_start": 0, "off_end": 76, "para_id": 21}]}, {"text": "Орын истукун некив ою аӈандин - тунынимӈыв, дюганимӈыв.", "words": [{"wf": "Орын", "off_start": 0, "off_end": 4, "wtype": "word", "ana": [{"parts": "orən", "gloss": "олень", "gloss_index": "олень{orən}-"}], "next_word": 1, "sentence_index": 0, "sentence_index_neg": 7}, {"wf": "истукун", "off_start": 5, "off_end": 12, "wtype": "word", "ana": [{"parts": "istukun", "gloss": "IDK", "gloss_index": "IDK{istukun}-"}], "next_word": 2, "sentence_index": 1, "sentence_index_neg": 6}, {"wf": "некив", "off_start": 13, "off_end": 18, "wtype": "word", "ana": [{"parts": "n'ekiw", "gloss": "IDK", "gloss_index": "IDK{n'ekiw}-"}], "next_word": 3, "sentence_index": 2, "sentence_index_neg": 5}, {"wf": "ою", "off_start": 19, "off_end": 21, "wtype": "word", "ana": [{"parts": "oju", "gloss": "IDK", "gloss_index": "IDK{oju}-"}], "next_word": 4, "sentence_index": 3, "sentence_index_neg": 4}, {"wf": "аӈандин", "off_start": 22, "off_end": 29, "wtype": "word", "ana": [{"parts": "aŋand'in", "gloss": "IDK", "gloss_index": "IDK{aŋand'in}-"}], "next_word": 5, "sentence_index": 4, "sentence_index_neg": 3}, {"wf": "тунынимӈыв,", "off_start": 32, "off_end": 43, "wtype": "word", "ana": [{"parts": "tunənimŋəw", "gloss": "IDK", "gloss_index": "IDK{tunənimŋəw}-"}], "next_word": 6, "sentence_index": 5, "sentence_index_neg": 2}, {"wf": "дюганимӈыв.", "off_start": 44, "off_end": 55, "wtype": "word", "ana": [{"parts": "d'uganimŋəw", "gloss": "IDK", "gloss_index": "IDK{d'uganimŋəw}-"}], "next_word": 7, "sentence_index": 6, "sentence_index_neg": 1}], "lang": 0, "para_alignment": [{"off_start": 0, "off_end": 55, "para_id": 22}]}, {"text": "Аӈны ис бидэн эсидин эллыв амуттиди имрэнун.", "words": [{"wf": "Аӈны", "off_start": 0, "off_end": 4, "wtype": "word", "ana": [{"parts": "aŋnə", "gloss": "IDK", "gloss_index": "IDK{aŋnə}-"}], "next_word": 1, "sentence_index": 0, "sentence_index_neg": 7}, {"wf": "ис", "off_start": 5, "off_end": 7, "wtype": "word", "ana": [{"parts": "is", "gloss": "IDK", "gloss_index": "IDK{is}-"}], "next_word": 2, "sentence_index": 1, "sentence_index_neg": 6}, {"wf": "бидэн", "off_start": 8, "off_end": 13, "wtype": "word", "ana": [{"parts": "bi-de-n", "gloss": "быть-nfut-3sg", "gloss_index": "быть{bi}-nfut{de}-3sg{n}-"}], "next_word": 3, "sentence_index": 2, "sentence_index_neg": 5}, {"wf": "эсидин", "off_start": 14, "off_end": 20, "wtype": "word", "ana": [{"parts": "esid'in", "gloss": "IDK", "gloss_index": "IDK{esid'in}-"}], "next_word": 4, "sentence_index": 3, "sentence_index_neg": 4}, {"wf": "эллыв", "off_start": 21, "off_end": 26, "wtype": "word", "ana": [{"parts": "elləw", "gloss": "IDK", "gloss_index": "IDK{elləw}-"}], "next_word": 5, "sentence_index": 4, "sentence_index_neg": 3}, {"wf": "амуттиди", "off_start": 27, "off_end": 35, "wtype": "word", "ana": [{"parts": "amuttid'i", "gloss": "IDK", "gloss_index": "IDK{amuttid'i}-"}], "next_word": 6, "sentence_index": 5, "sentence_index_neg": 2}, {"wf": "имрэнун.", "off_start": 36, "off_end": 44, "wtype": "word", "ana": [{"parts": "imrenun", "gloss": "IDK", "gloss_index": "IDK{imrenun}-"}], "next_word": 7, "sentence_index": 6, "sentence_index_neg": 1}], "lang": 0, "para_alignment": [{"off_start": 0, "off_end": 44, "para_id": 23}]}, {"text": "Н.Григорьева, авай.", "words": [{"wf": "Н.Григорьева,", "off_start": 0, "off_end": 13, "wtype": "word", "ana": [{"parts": "n.grigor'jewa", "gloss": "IDK", "gloss_index": "IDK{n.grigor'jewa}-"}], "next_word": 1, "sentence_index": 0, "sentence_index_neg": 2}, {"wf": "авай.", "off_start": 14, "off_end": 19, "wtype": "word", "ana": [{"parts": "awaj", "gloss": "знающий", "gloss_index": "знающий{awaj}-"}], "next_word": 2, "sentence_index": 1, "sentence_index_neg": 1}], "lang": 0, "para_alignment": [{"off_start": 0, "off_end": 19, "para_id": 24}]}, {"text": "Фото О.Кочеткова.", "words": [{"wf": "Фото", "off_start": 0, "off_end": 4, "wtype": "word", "ana": [{"parts": "foto", "gloss": "фото", "gloss_index": "фото{foto}-"}], "next_word": 1, "sentence_index": 0, "sentence_index_neg": 2}, {"wf": "О.Кочеткова.", "off_start": 5, "off_end": 17, "wtype": "word", "ana": [{"parts": "o.kočetkowa", "gloss": "IDK", "gloss_index": "IDK{o.kočetkowa}-"}], "next_word": 2, "sentence_index": 1, "sentence_index_neg": 1}], "lang": 0, "para_alignment": [{"off_start": 0, "off_end": 17, "para_id": 25}]}, {"text": "Перевод появится", "words": [{"wf": "Перевод", "off_start": 0, "off_end": 7, "wtype": "word", "next_word": 1, "sentence_index": 0, "sentence_index_neg": 2}, {"wf": "появится", "off_start": 8, "off_end": 16, "wtype": "word", "next_word": 2, "sentence_index": 1, "sentence_index_neg": 1}], "lang": 1, "para_alignment": [{"off_start": 0, "off_end": 16, "para_id": 0}]}, {"text": "Перевод появится", "words": [{"wf": "Перевод", "off_start": 0, "off_end": 7, "wtype": "word", "next_word": 1, "sentence_index": 0, "sentence_index_neg": 2}, {"wf": "появится", "off_start": 8, "off_end": 16, "wtype": "word", "next_word": 2, "sentence_index": 1, "sentence_index_neg": 1}], "lang": 1, "para_alignment": [{"off_start": 0, "off_end": 16, "para_id": 1}]}, {"text": "Перевод появится", "words": [{"wf": "Перевод", "off_start": 0, "off_end": 7, "wtype": "word", "next_word": 1, "sentence_index": 0, "sentence_index_neg": 2}, {"wf": "появится", "off_start": 8, "off_end": 16, "wtype": "word", "next_word": 2, "sentence_index": 1, "sentence_index_neg": 1}], "lang": 1, "para_alignment": [{"off_start": 0, "off_end": 16, "para_id": 2}]}, {"text": "Перевод появится", "words": [{"wf": "Перевод", "off_start": 0, "off_end": 7, "wtype": "word", "next_word": 1, "sentence_index": 0, "sentence_index_neg": 2}, {"wf": "появится", "off_start": 8, "off_end": 16, "wtype": "word", "next_word": 2, "sentence_index": 1, "sentence_index_neg": 1}], "lang": 1, "para_alignment": [{"off_start": 0, "off_end": 16, "para_id": 3}]}, {"text": "Перевод появится", "words": [{"wf": "Перевод", "off_start": 0, "off_end": 7, "wtype": "word", "next_word": 1, "sentence_index": 0, "sentence_index_neg": 2}, {"wf": "появится", "off_start": 8, "off_end": 16, "wtype": "word", "next_word": 2, "sentence_index": 1, "sentence_index_neg": 1}], "lang": 1, "para_alignment": [{"off_start": 0, "off_end": 16, "para_id": 4}]}, {"text": "Перевод появится", "words": [{"wf": "Перевод", "off_start": 0, "off_end": 7, "wtype": "word", "next_word": 1, "sentence_index": 0, "sentence_index_neg": 2}, {"wf": "появится", "off_start": 8, "off_end": 16, "wtype": "word", "next_word": 2, "sentence_index": 1, "sentence_index_neg": 1}], "lang": 1, "para_alignment": [{"off_start": 0, "off_end": 16, "para_id": 5}]}, {"text": "Перевод появится", "words": [{"wf": "Перевод", "off_start": 0, "off_end": 7, "wtype": "word", "next_word": 1, "sentence_index": 0, "sentence_index_neg": 2}, {"wf": "появится", "off_start": 8, "off_end": 16, "wtype": "word", "next_word": 2, "sentence_index": 1, "sentence_index_neg": 1}], "lang": 1, "para_alignment": [{"off_start": 0, "off_end": 16, "para_id": 6}]}, {"text": "Перевод появится", "words": [{"wf": "Перевод", "off_start": 0, "off_end": 7, "wtype": "word", "next_word": 1, "sentence_index": 0, "sentence_index_neg": 2}, {"wf": "появится", "off_start": 8, "off_end": 16, "wtype": "word", "next_word": 2, "sentence_index": 1, "sentence_index_neg": 1}], "lang": 1, "para_alignment": [{"off_start": 0, "off_end": 16, "para_id": 7}]}, {"text": "Перевод появится", "words": [{"wf": "Перевод", "off_start": 0, "off_end": 7, "wtype": "word", "next_word": 1, "sentence_index": 0, "sentence_index_neg": 2}, {"wf": "появится", "off_start": 8, "off_end": 16, "wtype": "word", "next_word": 2, "sentence_index": 1, "sentence_index_neg": 1}], "lang": 1, "para_alignment": [{"off_start": 0, "off_end": 16, "para_id": 8}]}, {"text": "Перевод появится", "words": [{"wf": "Перевод", "off_start": 0, "off_end": 7, "wtype": "word", "next_word": 1, "sentence_index": 0, "sentence_index_neg": 2}, {"wf": "появится", "off_start": 8, "off_end": 16, "wtype": "word", "next_word": 2, "sentence_index": 1, "sentence_index_neg": 1}], "lang": 1, "para_alignment": [{"off_start": 0, "off_end": 16, "para_id": 9}]}, {"text": "Перевод появится", "words": [{"wf": "Перевод", "off_start": 0, "off_end": 7, "wtype": "word", "next_word": 1, "sentence_index": 0, "sentence_index_neg": 2}, {"wf": "появится", "off_start": 8, "off_end": 16, "wtype": "word", "next_word": 2, "sentence_index": 1, "sentence_index_neg": 1}], "lang": 1, "para_alignment": [{"off_start": 0, "off_end": 16, "para_id": 10}]}, {"text": "Перевод появится", "words": [{"wf": "Перевод", "off_start": 0, "off_end": 7, "wtype": "word", "next_word": 1, "sentence_index": 0, "sentence_index_neg": 2}, {"wf": "появится", "off_start": 8, "off_end": 16, "wtype": "word", "next_word": 2, "sentence_index": 1, "sentence_index_neg": 1}], "lang": 1, "para_alignment": [{"off_start": 0, "off_end": 16, "para_id": 11}]}, {"text": "Перевод появится", "words": [{"wf": "Перевод", "off_start": 0, "off_end": 7, "wtype": "word", "next_word": 1, "sentence_index": 0, "sentence_index_neg": 2}, {"wf": "появится", "off_start": 8, "off_end": 16, "wtype": "word", "next_word": 2, "sentence_index": 1, "sentence_index_neg": 1}], "lang": 1, "para_alignment": [{"off_start": 0, "off_end": 16, "para_id": 12}]}, {"text": "Перевод появится", "words": [{"wf": "Перевод", "off_start": 0, "off_end": 7, "wtype": "word", "next_word": 1, "sentence_index": 0, "sentence_index_neg": 2}, {"wf": "появится", "off_start": 8, "off_end": 16, "wtype": "word", "next_word": 2, "sentence_index": 1, "sentence_index_neg": 1}], "lang": 1, "para_alignment": [{"off_start": 0, "off_end": 16, "para_id": 13}]}, {"text": "Перевод появится", "words": [{"wf": "Перевод", "off_start": 0, "off_end": 7, "wtype": "word", "next_word": 1, "sentence_index": 0, "sentence_index_neg": 2}, {"wf": "появится", "off_start": 8, "off_end": 16, "wtype": "word", "next_word": 2, "sentence_index": 1, "sentence_index_neg": 1}], "lang": 1, "para_alignment": [{"off_start": 0, "off_end": 16, "para_id": 14}]}, {"text": "Перевод появится", "words": [{"wf": "Перевод", "off_start": 0, "off_end": 7, "wtype": "word", "next_word": 1, "sentence_index": 0, "sentence_index_neg": 2}, {"wf": "появится", "off_start": 8, "off_end": 16, "wtype": "word", "next_word": 2, "sentence_index": 1, "sentence_index_neg": 1}], "lang": 1, "para_alignment": [{"off_start": 0, "off_end": 16, "para_id": 15}]}, {"text": "Перевод появится", "words": [{"wf": "Перевод", "off_start": 0, "off_end": 7, "wtype": "word", "next_word": 1, "sentence_index": 0, "sentence_index_neg": 2}, {"wf": "появится", "off_start": 8, "off_end": 16, "wtype": "word", "next_word": 2, "sentence_index": 1, "sentence_index_neg": 1}], "lang": 1, "para_alignment": [{"off_start": 0, "off_end": 16, "para_id": 16}]}, {"text": "Перевод появится", "words": [{"wf": "Перевод", "off_start": 0, "off_end": 7, "wtype": "word", "next_word": 1, "sentence_index": 0, "sentence_index_neg": 2}, {"wf": "появится", "off_start": 8, "off_end": 16, "wtype": "word", "next_word": 2, "sentence_index": 1, "sentence_index_neg": 1}], "lang": 1, "para_alignment": [{"off_start": 0, "off_end": 16, "para_id": 17}]}, {"text": "Перевод появится", "words": [{"wf": "Перевод", "off_start": 0, "off_end": 7, "wtype": "word", "next_word": 1, "sentence_index": 0, "sentence_index_neg": 2}, {"wf": "появится", "off_start": 8, "off_end": 16, "wtype": "word", "next_word": 2, "sentence_index": 1, "sentence_index_neg": 1}], "lang": 1, "para_alignment": [{"off_start": 0, "off_end": 16, "para_id": 18}]}, {"text": "Перевод появится", "words": [{"wf": "Перевод", "off_start": 0, "off_end": 7, "wtype": "word", "next_word": 1, "sentence_index": 0, "sentence_index_neg": 2}, {"wf": "появится", "off_start": 8, "off_end": 16, "wtype": "word", "next_word": 2, "sentence_index": 1, "sentence_index_neg": 1}], "lang": 1, "para_alignment": [{"off_start": 0, "off_end": 16, "para_id": 19}]}, {"text": "Перевод появится", "words": [{"wf": "Перевод", "off_start": 0, "off_end": 7, "wtype": "word", "next_word": 1, "sentence_index": 0, "sentence_index_neg": 2}, {"wf": "появится", "off_start": 8, "off_end": 16, "wtype": "word", "next_word": 2, "sentence_index": 1, "sentence_index_neg": 1}], "lang": 1, "para_alignment": [{"off_start": 0, "off_end": 16, "para_id": 20}]}, {"text": "Перевод появится", "words": [{"wf": "Перевод", "off_start": 0, "off_end": 7, "wtype": "word", "next_word": 1, "sentence_index": 0, "sentence_index_neg": 2}, {"wf": "появится", "off_start": 8, "off_end": 16, "wtype": "word", "next_word": 2, "sentence_index": 1, "sentence_index_neg": 1}], "lang": 1, "para_alignment": [{"off_start": 0, "off_end": 16, "para_id": 21}]}, {"text": "Перевод появится", "words": [{"wf": "Перевод", "off_start": 0, "off_end": 7, "wtype": "word", "next_word": 1, "sentence_index": 0, "sentence_index_neg": 2}, {"wf": "появится", "off_start": 8, "off_end": 16, "wtype": "word", "next_word": 2, "sentence_index": 1, "sentence_index_neg": 1}], "lang": 1, "para_alignment": [{"off_start": 0, "off_end": 16, "para_id": 22}]}, {"text": "Перевод появится", "words": [{"wf": "Перевод", "off_start": 0, "off_end": 7, "wtype": "word", "next_word": 1, "sentence_index": 0, "sentence_index_neg": 2}, {"wf": "появится", "off_start": 8, "off_end": 16, "wtype": "word", "next_word": 2, "sentence_index": 1, "sentence_index_neg": 1}], "lang": 1, "para_alignment": [{"off_start": 0, "off_end": 16, "para_id": 23}]}, {"text": "Перевод появится", "words": [{"wf": "Перевод", "off_start": 0, "off_end": 7, "wtype": "word", "next_word": 1, "sentence_index": 0, "sentence_index_neg": 2}, {"wf": "появится", "off_start": 8, "off_end": 16, "wtype": "word", "next_word": 2, "sentence_index": 1, "sentence_index_neg": 1}], "lang": 1, "para_alignment": [{"off_start": 0, "off_end": 16, "para_id": 24}]}, {"text": "Перевод появится", "words": [{"wf": "Перевод", "off_start": 0, "off_end": 7, "wtype": "word", "next_word": 1, "sentence_index": 0, "sentence_index_neg": 2}, {"wf": "появится", "off_start": 8, "off_end": 16, "wtype": "word", "next_word": 2, "sentence_index": 1, "sentence_index_neg": 1}], "lang": 1, "para_alignment": [{"off_start": 0, "off_end": 16, "para_id": 25}]}]}